Workbook

Sheet Cover
B3: Knowledge Marine & Engineering Works Ltd.
B12: Financials Databook

Sheet CF Dashboard
A1: =+Cover!B3 -> Knowledge Marine & Engineering Works Ltd.
A3: Dashboard | L3: CAGR
A4: Rs mm | B4: Units | C4: Mar-18 (A) | D4: Mar-19 (A) | E4: Mar-20 (A) | F4: Mar-21 (A) | G4: Mar-22 (A) | H4: Mar-23 (A) | I4: Mar-24 (A) | J4: Mar-25(A) | L4: 18-24
C5: Consolidated | D5: Consolidated | E5: Consolidated | F5: Consolidated | G5: Consolidated | H5: Consolidated | I5: Consolidated | J5: Consolidated
A6: Year end share price | B6: Rs | C6: 0 | D6: 0 | E6: 0 | F6: 37 | G6: 172.95 | H6: 901.45 | I6: 1405.8 | J6: 1665.15
A7: Market cap | B7: Rs mm | C7: =C6*C31 -> 0 | D7: =D6*D31 -> 0 | E7: =E6*E31 -> 0 | F7: =F6*F31 -> 377.4 | G7: =G6*G31 -> 1764.09 | H7: =H6*H31 -> 9735.66 | I7: =I6*I31 -> 15182.64 | J7: =J6*J31 -> 17983.62
A8: Enterprise value | B8: Rs mm | C8: =+C7+C19 -> 76.186 | D8: =+D7+D19 -> 56.24 | E8: =+E7+E19 -> 164.55183 | F8: =+F7+F19 -> 450.666 | G8: =+G7+G19 -> 1826.63 | H8: =+H7+H19 -> 9443.303 | I8: =+I7+I19 -> 15304.24 | J8: =+J7+J19 -> 18893.03
A10: EV/EBITDA | B10: x | C10: =IF(C15=0,"NA",C8/C15) -> 2.9831238 | D10: =IF(D15=0,"NA",D8/D15) -> 1.3063879 | E10: =IF(E15=0,"NA",E8/E15) -> 2.1206148 | F10: =IF(F15=0,"NA",F8/F15) -> 3.4261278 | G10: =IF(G15=0,"NA",G8/G15) -> 5.6351033 | H10: =IF(H15=0,"NA",H8/H15) -> 13.748812 | I10: =IF(I15=0,"NA",I8/I15) -> 30.684947 | J10: =IF(J15=0,"NA",J8/J15) -> 24.155221
A11: P/E | B11: x | C11: =IF(C16=0,"NA",C7/C16) -> 0 | D11: =IF(D16=0,"NA",D7/D16) -> 0 | E11: =IF(E16=0,"NA",E7/E16) -> 0 | F11: =IF(F16=0,"NA",F7/F16) -> 5.7847059 | G11: =IF(G16=0,"NA",G7/G16) -> 9.0992511 | H11: =IF(H16=0,"NA",H7/H16) -> 20.892288 | I11: =IF(I16=0,"NA",I7/I16) -> 55.728381 | J11: =IF(J16=0,"NA",J7/J16) -> 36.256275
A12: P/BV | B12: x | C12: =IF(C18=0,"NA",C7/C18) -> 0 | D12: =IF(D18=0,"NA",D7/D18) -> 0 | E12: =IF(E18=0,"NA",E7/E18) -> 0 | F12: =IF(F18=0,"NA",F7/F18) -> 1.3974207 | G12: =IF(G18=0,"NA",G7/G18) -> 3.7244826 | H12: =IF(H18=0,"NA",H7/H18) -> 7.2653095 | I12: =IF(I18=0,"NA",I7/I18) -> 9.0863683 | J12: =IF(J18=0,"NA",J7/J18) -> 8.270179
A14: Revenue | B14: Rs mm | C14: ='CF IS'!C6 -> 106.009 | D14: ='CF IS'!D6 -> 105.672 | E14: ='CF IS'!E6 -> 239.08809 | F14: ='CF IS'!F6 -> 332.822 | G14: ='CF IS'!G6 -> 611.063 | H14: ='CF IS'!H6 -> 2015.296 | I14: ='CF IS'!I6 -> 1635.831 | J14: ='CF IS'!J6 -> 2007.067 | L14: =+IFERROR(_xlfn.RRI(6,C14,I14),"NA") -> 0.57785085
A15: EBITDA | B15: Rs mm | C15: ='CF IS'!C14 -> 25.539 | D15: ='CF IS'!D14 -> 43.05 | E15: ='CF IS'!E14 -> 77.596288 | F15: ='CF IS'!F14 -> 131.538 | G15: ='CF IS'!G14 -> 324.152 | H15: ='CF IS'!H14 -> 686.845 | I15: ='CF IS'!I14 -> 498.754 | J15: ='CF IS'!J14 -> 782.151 | L15: =+IFERROR(_xlfn.RRI(6,C15,I15),"NA") -> 0.64101953
A16: Net income | B16: Rs mm | C16: ='CF IS'!C27 -> 13.18 | D16: ='CF IS'!D27 -> 19.016 | E16: ='CF IS'!E27 -> 34.54286 | F16: ='CF IS'!F27 -> 65.241 | G16: ='CF IS'!G27 -> 193.872 | H16: ='CF IS'!H27 -> 465.993 | I16: ='CF IS'!I27 -> 272.44 | J16: ='CF IS'!J27 -> 496.014 | L16: =+IFERROR(_xlfn.RRI(6,C16,I16),"NA") -> 0.65663148
A18: Net worth | B18: Rs mm | C18: ='CF BS'!C10 -> 20.339 | D18: ='CF BS'!D10 -> 64.256 | E18: ='CF BS'!E10 -> 104.2324 | F18: ='CF BS'!F10 -> 270.069 | G18: ='CF BS'!G10 -> 473.647 | H18: ='CF BS'!H10 -> 1340.02 | I18: ='CF BS'!I10 -> 1670.925 | J18: ='CF BS'!J10 -> 2174.514
A19: Net debt | B19: Rs mm | C19: ='CF BS'!C16-'CF BS'!C38+'CF BS'!C12 -> 76.186 | D19: ='CF BS'!D16-'CF BS'!D38+'CF BS'!D12 -> 56.24 | E19: ='CF BS'!E16-'CF BS'!E38+'CF BS'!E12 -> 164.55183 | F19: ='CF BS'!F16-'CF BS'!F38+'CF BS'!F12 -> 73.266 | G19: ='CF BS'!G16-'CF BS'!G38+'CF BS'!G12 -> 62.54 | H19: ='CF BS'!H16-'CF BS'!H38+'CF BS'!H12 -> -292.357 | I19: ='CF BS'!I16-'CF BS'!I38+'CF BS'!I12 -> 121.6 | J19: ='CF BS'!J16-'CF BS'!J38+'CF BS'!J12 -> 909.41
A21: Free cash flow¹ | B21: Rs mm | C21: ='CF CFS'!C42 -> 28.282 | D21: ='CF CFS'!D42 -> 107.082 | E21: ='CF CFS'!E42 -> 8.577225 | F21: ='CF CFS'!F42 -> 31.269 | G21: ='CF CFS'!G42 -> 321.081 | H21: ='CF CFS'!H42 -> 188.879 | I21: ='CF CFS'!I42 -> 304.824 | J21: ='CF CFS'!J42 -> 578.393
A23: Book value per share | B23: Rs | C23: =IF(C31=0,"NA",C18/C31) -> NA | D23: =IF(D31=0,"NA",D18/D31) -> 25.7024 | E23: =IF(E31=0,"NA",E18/E31) -> 41.692962 | F23: =IF(F31=0,"NA",F18/F31) -> 26.477353 | G23: =IF(G31=0,"NA",G18/G31) -> 46.43598 | H23: =IF(H31=0,"NA",H18/H31) -> 124.07593 | I23: =IF(I31=0,"NA",I18/I31) -> 154.71528 | J23: =IF(J31=0,"NA",J18/J31) -> 201.34389
A24: Earning per share | B24: Rs | C24: =IF(C31=0,"NA",C16/C31) -> NA | D24: =IF(D31=0,"NA",D16/D31) -> 7.6064 | E24: =IF(E31=0,"NA",E16/E31) -> 13.817144 | F24: =IF(F31=0,"NA",F16/F31) -> 6.3961765 | G24: =IF(G31=0,"NA",G16/G31) -> 19.007059 | H24: =IF(H31=0,"NA",H16/H31) -> 43.1475 | I24: =IF(I31=0,"NA",I16/I31) -> 25.225926 | J24: =IF(J31=0,"NA",J16/J31) -> 45.927222
A26: Cash conversion cycle | B26: No. days | C26: ='CF BS'!C60 -> 16.812676 | D26: ='CF BS'!D60 -> -228.2977 | E26: ='CF BS'!E60 -> -14.024707 | F26: ='CF BS'!F60 -> 61.086301 | G26: ='CF BS'!G60 -> -15.425783 | H26: ='CF BS'!H60 -> 54.636369 | I26: ='CF BS'!I60 -> 82.278072 | J26: ='CF BS'!J60 -> 85.160368
A28: ROCE | B28: % | C28: ='CF BS'!C49 -> NA | D28: ='CF BS'!D49 -> 0.32306551 | E28: ='CF BS'!E49 -> 0.32090635 | F28: ='CF BS'!F49 -> 0.36232483 | G28: ='CF BS'!G49 -> 0.68174986 | H28: ='CF BS'!H49 -> 0.81227768 | I28: ='CF BS'!I49 -> 0.30843029 | J28: ='CF BS'!J49 -> 0.27390177
A29: ROE | B29: % | C29: ='CF BS'!C50 -> NA | D29: ='CF BS'!D50 -> 0.4495774 | E29: ='CF BS'!E50 -> 0.41003249 | F29: ='CF BS'!F50 -> 0.34860142 | G29: ='CF BS'!G50 -> 0.5213603 | H29: ='CF BS'!H50 -> 0.51386831 | I29: ='CF BS'!I50 -> 0.18096644 | J29: ='CF BS'!J50 -> 0.25797523
A31: No. of shares outstanding | B31: Nos mm | C31: ='CF BS'!C62 -> 0 | D31: ='CF BS'!D62 -> 2.5 | E31: ='CF BS'!E62 -> 2.5 | F31: ='CF BS'!F62 -> 10.2 | G31: ='CF BS'!G62 -> 10.2 | H31: ='CF BS'!H62 -> 10.8 | I31: ='CF BS'!I62 -> 10.8 | J31: ='CF BS'!J62 -> 10.8
A32: Conversion rate (rs/$) | B32: Rs | C32: 65.0441 | D32: 69.1713 | E32: 76.1522 | F32: 73.5047 | G32: 75.8071 | H32: 82.2169 | I32: 83.3739 | J32: 85.58
A34: ¹ free cash flow = cash flow from operations (less) interest expense (less) maintenance capex

Sheet CF BS
B1: =+Cover!B3 -> Knowledge Marine & Engineering Works Ltd.
B3: Balance Sheet
B4: Rs mm | C4: Mar-18(A) | D4: Mar-19(A) | E4: Mar-20(A) | F4: Mar-21(A) | G4: Mar-22(A) | H4: Mar-23(A) | I4: Mar-24(A) | J4: Mar-25(A)
C5: ='Working capital'!C5 -> Consolidated | D5: ='Working capital'!D5 -> Consolidated | E5: ='Working capital'!E5 -> Consolidated | F5: ='Working capital'!F5 -> Consolidated | G5: ='Working capital'!G5 -> Consolidated | H5: ='Working capital'!H5 -> Consolidated | I5: ='Working capital'!I5 -> Consolidated | J5: =I5 -> Consolidated
B6: Share capital | C6: ='Equity & reserves'!C20 -> 0.1 | D6: ='Equity & reserves'!D20 -> 25 | E6: ='Equity & reserves'!E20 -> 25 | F6: ='Equity & reserves'!F20 -> 102.36 | G6: ='Equity & reserves'!G20 -> 102.36 | H6: ='Equity & reserves'!H20 -> 108.01 | I6: ='Equity & reserves'!I20 -> 108.01 | J6: 108.01
B7: Share warrants | C7: ='Equity & reserves'!C22 -> 0 | D7: ='Equity & reserves'!D22 -> 0 | E7: ='Equity & reserves'!E22 -> 0 | F7: ='Equity & reserves'!F22 -> 0 | G7: ='Equity & reserves'!G22 -> 0 | H7: ='Equity & reserves'!H22 -> 0 | I7: ='Equity & reserves'!I22 -> 0 | J7: ='Equity & reserves'!J22 -> 0
B8: Revaluation reserve | C8: ='Equity & reserves'!C50 -> 0 | D8: ='Equity & reserves'!D50 -> 0 | E8: ='Equity & reserves'!E50 -> 0 | F8: ='Equity & reserves'!F50 -> 0 | G8: ='Equity & reserves'!G50 -> 0 | H8: ='Equity & reserves'!H50 -> 0 | I8: ='Equity & reserves'!I50 -> 0 | J8: ='Equity & reserves'!J50 -> 0
B9: Reserves & surplus | C9: ='Equity & reserves'!C47 -> 20.239 | D9: ='Equity & reserves'!D47 -> 39.256 | E9: ='Equity & reserves'!E47 -> 79.232405 | F9: ='Equity & reserves'!F47 -> 167.709 | G9: ='Equity & reserves'!G47 -> 371.287 | H9: ='Equity & reserves'!H47 -> 1232.01 | I9: ='Equity & reserves'!I47 -> 1562.915 | J9: 2066.504
B10: Total common equity | C10: =SUM(C6:C9) -> 20.339 | D10: =SUM(D6:D9) -> 64.256 | E10: =SUM(E6:E9) -> 104.2324 | F10: =SUM(F6:F9) -> 270.069 | G10: =SUM(G6:G9) -> 473.647 | H10: =SUM(H6:H9) -> 1340.02 | I10: =SUM(I6:I9) -> 1670.925 | J10: =SUM(J6:J9) -> 2174.514
B12: Minority interest | C12: ='Equity & reserves'!C55 -> 8.732 | D12: ='Equity & reserves'!D55 -> 16.807 | E12: ='Equity & reserves'!E55 -> 19.425947 | F12: ='Equity & reserves'!F55 -> 19.142 | G12: ='Equity & reserves'!G55 -> 24.242 | H12: ='Equity & reserves'!H55 -> 26.189 | I12: ='Equity & reserves'!I55 -> 25.644 | J12: 24.341
B14: Long term borrowings | C14: =Borrowings!C76 -> 43.146 | D14: =Borrowings!D76 -> 74.086 | E14: =Borrowings!E76 -> 110.39248 | F14: =Borrowings!F76 -> 116.353 | G14: =Borrowings!G76 -> 171.758 | H14: =Borrowings!H76 -> 42.058 | I14: =Borrowings!I76 -> 417.48 | J14: 675.691
B15: Short term borrowings | C15: =Borrowings!C124 -> 26.061 | D15: =Borrowings!D124 -> 39.55 | E15: =Borrowings!E124 -> 50.94657 | F15: =Borrowings!F124 -> 53.083 | G15: =Borrowings!G124 -> 92.231 | H15: =Borrowings!H124 -> 199.3 | I15: =Borrowings!I124 -> 184.468 | J15: 659.109
B16: Borrowings | C16: =SUM(C14:C15) -> 69.207 | D16: =SUM(D14:D15) -> 113.636 | E16: =SUM(E14:E15) -> 161.33905 | F16: =SUM(F14:F15) -> 169.436 | G16: =SUM(G14:G15) -> 263.989 | H16: =SUM(H14:H15) -> 241.358 | I16: =SUM(I14:I15) -> 601.948 | J16: =SUM(J14:J15) -> 1334.8
B18: Accounts payable | C18: ='Working capital'!C15 -> 8.203 | D18: ='Working capital'!D15 -> 71.466 | E18: ='Working capital'!E15 -> 25.932757 | F18: ='Working capital'!F15 -> 4.978 | G18: ='Working capital'!G15 -> 61.682 | H18: ='Working capital'!H15 -> 261.048 | I18: ='Working capital'!I15 -> 121.705 | J18: 229.834
B19: Provisions | C19: ='Working capital'!C25 -> 11.306 | D19: ='Working capital'!D25 -> 10.599 | E19: ='Working capital'!E25 -> 13.539071 | F19: ='Working capital'!F25 -> 22.422 | G19: ='Working capital'!G25 -> 67.878 | H19: ='Working capital'!H25 -> 153.872 | I19: ='Working capital'!I25 -> 94.316 | J19: =(28+315.38)/10 -> 34.338
B20: Other current liability | C20: ='Working capital'!C20 -> 0 | D20: ='Working capital'!D20 -> 0 | E20: ='Working capital'!E20 -> 21.121722 | F20: ='Working capital'!F20 -> 2.448 | G20: ='Working capital'!G20 -> 13.904 | H20: ='Working capital'!H20 -> 21.124 | I20: ='Working capital'!I20 -> 13.073 | J20: 106.891
B21: Defered tax liability/(assets) | C21: ='Other liabilities'!C27 -> 3.713 | D21: ='Other liabilities'!D27 -> 3.671 | E21: ='Other liabilities'!E27 -> 9.473117 | F21: ='Other liabilities'!F27 -> 21.39 | G21: ='Other liabilities'!G27 -> 30.528 | H21: ='Other liabilities'!H27 -> 43.611 | I21: ='Other liabilities'!I27 -> 55.338 | J21: 82.555
B22: Other non-current liabilities | C22: ='Other liabilities'!C53 -> 19.429 | D22: ='Other liabilities'!D53 -> 19.01 | E22: ='Other liabilities'!E53 -> 0 | F22: ='Other liabilities'!F53 -> 0.473 | G22: ='Other liabilities'!G53 -> 0.926 | H22: ='Other liabilities'!H53 -> 1.616 | I22: ='Other liabilities'!I53 -> 2.112 | J22: ='Other liabilities'!J53 -> 0
B23: Liabilites | C23: =SUM(C18:C22) -> 42.651 | D23: =SUM(D18:D22) -> 104.746 | E23: =SUM(E18:E22) -> 70.066667 | F23: =SUM(F18:F22) -> 51.711 | G23: =SUM(G18:G22) -> 174.918 | H23: =SUM(H18:H22) -> 481.271 | I23: =SUM(I18:I22) -> 286.544 | J23: =SUM(J18:J22) -> 453.618
B25: Total liabilities and equity | C25: =C10+C12+C16+C23 -> 140.929 | D25: =D10+D12+D16+D23 -> 299.445 | E25: =E10+E12+E16+E23 -> 355.06407 | F25: =F10+F12+F16+F23 -> 510.358 | G25: =G10+G12+G16+G23 -> 936.796 | H25: =H10+H12+H16+H23 -> 2088.838 | I25: =I10+I12+I16+I23 -> 2585.061 | J25: =J10+J12+J16+J23 -> 3987.273
B27: Assets
B28: Gross property, plant & equipment | C28: =PPE!C16 -> 116.68 | D28: =PPE!D16 -> 136.211 | E28: =PPE!E16 -> 297.29131 | F28: =PPE!F16 -> 322.608 | G28: =PPE!G16 -> 595.309 | H28: =PPE!H16 -> 701.45 | I28: =PPE!I16 -> 1240.741 | J28: =PPE!J16 -> 0
B29: Accumulated depreciation | C29: =(PPE!C28+PPE!C30) -> -3.113 | D29: =(PPE!D28+PPE!D30) -> -14.252 | E29: =(PPE!E28+PPE!E30) -> -24.571 | F29: =(PPE!F28+PPE!F30) -> -44.998 | G29: =(PPE!G28+PPE!G30) -> -69.55 | H29: =(PPE!H28+PPE!H30) -> -113.145 | I29: =(PPE!I28+PPE!I30) -> -173.898 | J29: =(PPE!J28+PPE!J30) -> 0
B30: Net property, plant & equipment | C30: =SUM(C28:C29) -> 113.567 | D30: =SUM(D28:D29) -> 121.959 | E30: =SUM(E28:E29) -> 272.72031 | F30: =SUM(F28:F29) -> 277.61 | G30: =SUM(G28:G29) -> 525.759 | H30: =SUM(H28:H29) -> 588.305 | I30: =SUM(I28:I29) -> 1066.843 | J30: =(15926.31+0.09+2.24)/10 -> 1592.864
B32: Capital work in progress | C32: =SUM(PPE!C44:C48) -> 0 | D32: =SUM(PPE!D44:D48) -> 75.286 | E32: =SUM(PPE!E44:E48) -> 0 | F32: =SUM(PPE!F44:F48) -> 28.536 | G32: =SUM(PPE!G44:G48) -> 18.08 | H32: =SUM(PPE!H44:H48) -> 80.985 | I32: =SUM(PPE!I44:I48) -> 120.383 | J32: 501.54
B33: Non current investments | C33: ='Other assets'!C35 -> 0.798 | D33: ='Other assets'!D35 -> 11.06 | E33: ='Other assets'!E35 -> 14.723733 | F33: ='Other assets'!F35 -> 2.764 | G33: ='Other assets'!G35 -> 29.577 | H33: ='Other assets'!H35 -> 113.055 | I33: ='Other assets'!I35 -> 294.001 | J33: 603.448
B34: Other long term assets | C34: ='Other assets'!C47+'Other assets'!C57+'Other assets'!C81 -> 0.419 | D34: ='Other assets'!D47+'Other assets'!D57+'Other assets'!D81 -> 0.967 | E34: ='Other assets'!E47+'Other assets'!E57+'Other assets'!E81 -> 0 | F34: ='Other assets'!F47+'Other assets'!F57+'Other assets'!F81 -> 0 | G34: ='Other assets'!G47+'Other assets'!G57+'Other assets'!G81 -> 20.05 | H34: ='Other assets'!H47+'Other assets'!H57+'Other assets'!H81 -> 8.878 | I34: ='Other assets'!I47+'Other assets'!I57+'Other assets'!I81 -> 0 | J34: =(2.86+0.58+0.02)/10 -> 0.346
B35: Currents investments | C35: ='Working capital'!C28 -> 0 | D35: ='Working capital'!D28 -> 0 | E35: ='Working capital'!E28 -> 0 | F35: ='Working capital'!F28 -> 0.587 | G35: ='Working capital'!G28 -> 0 | H35: ='Working capital'!H28 -> 0 | I35: ='Working capital'!I28 -> 0 | J35: ='Working capital'!J28 -> 0
B36: Inventories | C36: ='Working capital'!C57 -> 0 | D36: ='Working capital'!D57 -> 0 | E36: ='Working capital'!E57 -> 2.695134 | F36: ='Working capital'!F57 -> 3.298 | G36: ='Working capital'!G57 -> 1.888 | H36: ='Working capital'!H57 -> 11.425 | I36: ='Working capital'!I57 -> 12.165 | J36: 9.781
B37: Sundry debtors | C37: ='Working capital'!C71 -> 16.506 | D37: ='Working capital'!D71 -> 10.303 | E37: ='Working capital'!E71 -> 30.294803 | F37: ='Working capital'!F71 -> 3.969 | G37: ='Working capital'!G71 -> 39.428 | H37: ='Working capital'!H71 -> 558.005 | I37: ='Working capital'!I71 -> 432.053 | J37: 719.285
B38: Cash and bank | C38: ='Other assets'!C69 -> 1.753 | D38: ='Other assets'!D69 -> 74.203 | E38: ='Other assets'!E69 -> 16.213161 | F38: ='Other assets'!F69 -> 115.312 | G38: ='Other assets'!G69 -> 225.691 | H38: ='Other assets'!H69 -> 559.904 | I38: ='Other assets'!I69 -> 505.992 | J38: =(1266.02+3231.29)/10 -> 449.731
B39: Other current assets | C39: ='Working capital'!C78 -> 0 | D39: ='Working capital'!D78 -> 0.408 | E39: ='Working capital'!E78 -> 0.029628 | F39: ='Working capital'!F78 -> 7.516 | G39: ='Working capital'!G78 -> 0.02 | H39: ='Working capital'!H78 -> 0.468 | I39: ='Working capital'!I78 -> 34.909 | J39: =(428.19+674.2)/10 -> 110.239
B40: Short term loans and advances | C40: ='Working capital'!C95 -> 7.886 | D40: ='Working capital'!D95 -> 5.259 | E40: ='Working capital'!E95 -> 18.387299 | F40: ='Working capital'!F95 -> 70.766 | G40: ='Working capital'!G95 -> 76.303 | H40: ='Working capital'!H95 -> 167.813 | I40: ='Working capital'!I95 -> 118.715 | J40: 0.039
B41: Total current assets | C41: =SUM(C35:C40) -> 26.145 | D41: =SUM(D35:D40) -> 90.173 | E41: =SUM(E35:E40) -> 67.620025 | F41: =SUM(F35:F40) -> 201.448 | G41: =SUM(G35:G40) -> 343.33 | H41: =SUM(H35:H40) -> 1297.615 | I41: =SUM(I35:I40) -> 1103.834 | J41: =SUM(J35:J40) -> 1289.075
B42: Total assets | C42: =C30+C32+C33+C34+C41 -> 140.929 | D42: =D30+D32+D33+D34+D41 -> 299.445 | E42: =E30+E32+E33+E34+E41 -> 355.06407 | F42: =F30+F32+F33+F34+F41 -> 510.358 | G42: =G30+G32+G33+G34+G41 -> 936.796 | H42: =H30+H32+H33+H34+H41 -> 2088.838 | I42: =I30+I32+I33+I34+I41 -> 2585.061 | J42: =J30+J32+J33+J34+J41 -> 3987.273
B44: Conversion rate (rs/$) | C44: =+'CF Dashboard'!C32 -> 65.0441 | D44: =+'CF Dashboard'!D32 -> 69.1713 | E44: =+'CF Dashboard'!E32 -> 76.1522 | F44: =+'CF Dashboard'!F32 -> 73.5047 | G44: =+'CF Dashboard'!G32 -> 75.8071 | H44: =+'CF Dashboard'!H32 -> 82.2169 | I44: =+'CF Dashboard'!I32 -> 83.3739 | J44: =+'CF Dashboard'!J32 -> 85.58
B46: Check | C46: =C25-C42 -> 0 | D46: =D25-D42 -> 0 | E46: =E25-E42 -> 0 | F46: =F25-F42 -> 0 | G46: =G25-G42 -> 0 | H46: =H25-H42 -> 0 | I46: =I25-I42 -> 0 | J46: =J25-J42 -> 0
B48: Key ratios
B49: ROCE | C49: NA | D49: =IF(D10=0,"NA",'CF IS'!D16/AVERAGE((C10+C12+C16-C38),(D10+D12+D16-D38))) -> 0.32306551 | E49: =IF(E10=0,"NA",'CF IS'!E16/AVERAGE((D10+D12+D16-D38),(E10+E12+E16-E38))) -> 0.32090635 | F49: =IF(F10=0,"NA",'CF IS'!F16/AVERAGE((E10+E12+E16-E38),(F10+F12+F16-F38))) -> 0.36232483 | G49: =IF(G10=0,"NA",'CF IS'!G16/AVERAGE((F10+F12+F16-F38),(G10+G12+G16-G38))) -> 0.68174986 | H49: =IF(H10=0,"NA",'CF IS'!H16/AVERAGE((G10+G12+G16-G38),(H10+H12+H16-H38))) -> 0.81227768 | I49: =IF(I10=0,"NA",'CF IS'!I16/AVERAGE((H10+H12+H16-H38),(I10+I12+I16-I38))) -> 0.30843029 | J49: =IF(J10=0,"NA",'CF IS'!J16/AVERAGE((I10+I12+I16-I38),(J10+J12+J16-J38))) -> 0.27390177
B50: ROE | C50: NA | D50: =IF(D10=0,"NA",'CF IS'!D27/(AVERAGE(C10,D10))) -> 0.4495774 | E50: =IF(E10=0,"NA",'CF IS'!E27/(AVERAGE(D10,E10))) -> 0.41003249 | F50: =IF(F10=0,"NA",'CF IS'!F27/(AVERAGE(E10,F10))) -> 0.34860142 | G50: =IF(G10=0,"NA",'CF IS'!G27/(AVERAGE(F10,G10))) -> 0.5213603 | H50: =IF(H10=0,"NA",'CF IS'!H27/(AVERAGE(G10,H10))) -> 0.51386831 | I50: =IF(I10=0,"NA",'CF IS'!I27/(AVERAGE(H10,I10))) -> 0.18096644 | J50: =IF(J10=0,"NA",'CF IS'!J27/(AVERAGE(I10,J10))) -> 0.25797523
B52: Turnover ratios (days)
B53: Debtor/accounts receivable days¹ | C53: =IF(C37=0,"NA",C37/'CF IS'!C6*365) -> 56.831873 | D53: =IF(D37=0,"NA",D37/'CF IS'!D6*365) -> 35.587431 | E53: =IF(E37=0,"NA",E37/'CF IS'!E6*365) -> 46.249076 | F53: =IF(F37=0,"NA",F37/'CF IS'!F6*365) -> 4.3527321 | G53: =IF(G37=0,"NA",G37/'CF IS'!G6*365) -> 23.551123 | H53: =IF(H37=0,"NA",H37/'CF IS'!H6*365) -> 101.06298 | I53: =IF(I37=0,"NA",I37/'CF IS'!I6*365) -> 96.403201 | J53: =IF(J37=0,"NA",J37/'CF IS'!J6*365) -> 130.8073
B54: Inventory days¹ | C54: =IF(C36=0,"NA",C36/'CF IS'!C6*365) -> NA | D54: =IF(D36=0,"NA",D36/'CF IS'!D6*365) -> NA | E54: =IF(E36=0,"NA",E36/'CF IS'!E6*365) -> 4.1144832 | F54: =IF(F36=0,"NA",F36/'CF IS'!F6*365) -> 3.6168583 | G54: =IF(G36=0,"NA",G36/'CF IS'!G6*365) -> 1.1277397 | H54: =IF(H36=0,"NA",H36/'CF IS'!H6*365) -> 2.069237 | I54: =IF(I36=0,"NA",I36/'CF IS'!I6*365) -> 2.7143544 | J54: =IF(J36=0,"NA",J36/'CF IS'!J6*365) -> 1.7787473
B55: Other current asset days | C55: =IF(C39=0,"NA",C39/'CF IS'!C6*365) -> NA | D55: =IF(D39=0,"NA",D39/'CF IS'!D6*365) -> 1.4092664 | E55: =IF(E39=0,"NA",E39/'CF IS'!E6*365) -> 0.045231112 | F55: =IF(F39=0,"NA",F39/'CF IS'!F6*365) -> 8.2426642 | G55: =IF(G39=0,"NA",G39/'CF IS'!G6*365) -> 0.011946395 | H55: =IF(H39=0,"NA",H39/'CF IS'!H6*365) -> 0.084761742 | I55: =IF(I39=0,"NA",I39/'CF IS'!I6*365) -> 7.7891818 | J55: =IF(J39=0,"NA",J39/'CF IS'!J6*365) -> 20.047779
B56: Short term loans/advances days | C56: =IFERROR((IF(C40=0, "NA", C40/'CF IS'!C6*365)), "NA") -> 27.152317 | D56: =IFERROR((IF(D40=0, "NA", D40/'CF IS'!D6*365)), "NA") -> 18.16503 | E56: =IFERROR((IF(E40=0, "NA", E40/'CF IS'!E6*365)), "NA") -> 28.070676 | F56: =IFERROR((IF(F40=0, "NA", F40/'CF IS'!F6*365)), "NA") -> 77.60782 | G56: =IFERROR((IF(G40=0, "NA", G40/'CF IS'!G6*365)), "NA") -> 45.577289 | H56: =IFERROR((IF(H40=0, "NA", H40/'CF IS'!H6*365)), "NA") -> 30.393424 | I56: =IFERROR((IF(I40=0, "NA", I40/'CF IS'!I6*365)), "NA") -> 26.488662 | J56: =IFERROR((IF(J40=0, "NA", J40/'CF IS'!J6*365)), "NA") -> 0.0070924389
B57: Creditor/accounts payable days¹ | C57: =IF(C18=0,"NA",-C18/'CF IS'!C6*365) -> -28.243781 | D57: =IF(D18=0,"NA",-D18/'CF IS'!D6*365) -> -246.84959 | E57: =IF(E18=0,"NA",-E18/'CF IS'!E6*365) -> -39.589828 | F57: =IF(F18=0,"NA",-F18/'CF IS'!F6*365) -> -5.4592845 | G57: =IF(G18=0,"NA",-G18/'CF IS'!G6*365) -> -36.843877 | H57: =IF(H18=0,"NA",-H18/'CF IS'!H6*365) -> -47.279665 | I57: =IF(I18=0,"NA",-I18/'CF IS'!I6*365) -> -27.155816 | J57: =IF(J18=0,"NA",-J18/'CF IS'!J6*365) -> -41.797015
B58: Other current liabilities days | C58: =IFERROR(IF(C20=0, "NA", -C20/'CF IS'!C6*365), "NA") -> NA | D58: =IFERROR(IF(D20=0, "NA", -D20/'CF IS'!D6*365), "NA") -> NA | E58: =IFERROR(IF(E20=0, "NA", -E20/'CF IS'!E6*365), "NA") -> -32.245139 | F58: =IFERROR(IF(F20=0, "NA", -F20/'CF IS'!F6*365), "NA") -> -2.6846783 | G58: =IFERROR(IF(G20=0, "NA", -G20/'CF IS'!G6*365), "NA") -> -8.3051338 | H58: =IFERROR(IF(H20=0, "NA", -H20/'CF IS'!H6*365), "NA") -> -3.8258697 | I58: =IFERROR(IF(I20=0, "NA", -I20/'CF IS'!I6*365), "NA") -> -2.9169547 | J58: =IFERROR(IF(J20=0, "NA", -J20/'CF IS'!J6*365), "NA") -> -19.43892
B59: Provision days | C59: =IFERROR(IF(C19=0, "NA", -C19/'CF IS'!C6*365), "NA") -> -38.927733 | D59: =IFERROR(IF(D19=0, "NA", -D19/'CF IS'!D6*365), "NA") -> -36.60984 | E59: =IFERROR(IF(E19=0, "NA", -E19/'CF IS'!E6*365), "NA") -> -20.669206 | F59: =IFERROR(IF(F19=0, "NA", -F19/'CF IS'!F6*365), "NA") -> -24.589811 | G59: =IFERROR(IF(G19=0, "NA", -G19/'CF IS'!G6*365), "NA") -> -40.54487 | H59: =IFERROR(IF(H19=0, "NA", -H19/'CF IS'!H6*365), "NA") -> -27.868502 | I59: =IFERROR(IF(I19=0, "NA", -I19/'CF IS'!I6*365), "NA") -> -21.044558 | J59: =IFERROR(IF(J19=0, "NA", -J19/'CF IS'!J6*365), "NA") -> -6.2446196
B60: Cash conversion days | C60: =SUM(C53:C59) -> 16.812676 | D60: =SUM(D53:D59) -> -228.2977 | E60: =SUM(E53:E59) -> -14.024707 | F60: =SUM(F53:F59) -> 61.086301 | G60: =SUM(G53:G59) -> -15.425783 | H60: =SUM(H53:H59) -> 54.636369 | I60: =SUM(I53:I59) -> 82.278072 | J60: =SUM(J53:J59) -> 85.160368
B61: ¹ turnover days calculated on sales during the given period.
B62: No. of shares (nos mm) | C62: 0 | D62: 2.5 | E62: 2.5 | F62: 10.2 | G62: 10.2 | H62: 10.8 | I62: 10.8 | J62: 10.8

Sheet CF IS
B1: =+Cover!B3 -> Knowledge Marine & Engineering Works Ltd.
B3: Income Statement
B4: Rs mm | C4: Mar-18 (A) | D4: Mar-19 (A) | E4: Mar-20 (A) | F4: Mar-21 (A) | G4: Mar-22 (A) | H4: Mar-23 (A) | I4: Mar-24 (A) | J4: Mar-25 (A) | L4: Q1FY26
C5: =Expenses!C5 -> Consolidated | D5: =Expenses!D5 -> Consolidated | E5: =Expenses!E5 -> Consolidated | F5: =Expenses!F5 -> Consolidated | G5: =Expenses!G5 -> Consolidated | H5: =Expenses!H5 -> Consolidated | I5: =Expenses!I5 -> Consolidated | J5: =I5 -> Consolidated | L5: =J5 -> Consolidated
B6: Revenue | C6: ='Revenue & OI'!C11 -> 106.009 | D6: ='Revenue & OI'!D11 -> 105.672 | E6: ='Revenue & OI'!E11 -> 239.08809 | F6: ='Revenue & OI'!F11 -> 332.822 | G6: ='Revenue & OI'!G11 -> 611.063 | H6: ='Revenue & OI'!H11 -> 2015.296 | I6: ='Revenue & OI'!I11 -> 1635.831 | J6: 2007.067 | L6: 484.745
B7: Cost of goods sold | C7: =-Expenses!C53 -> -60.72 | D7: =-Expenses!D53 -> -29.674 | E7: =-Expenses!E53 -> -122.2069 | F7: =-Expenses!F53 -> -160.8 | G7: =-Expenses!G53 -> -230.463 | H7: =-Expenses!H53 -> -1240.06 | I7: =-Expenses!I53 -> -988.119 | J7: -950.984 | L7: -227.786
B8: Gross profit | C8: =SUM(C6:C7) -> 45.289 | D8: =SUM(D6:D7) -> 75.998 | E8: =SUM(E6:E7) -> 116.88119 | F8: =SUM(F6:F7) -> 172.022 | G8: =SUM(G6:G7) -> 380.6 | H8: =SUM(H6:H7) -> 775.236 | I8: =SUM(I6:I7) -> 647.712 | J8: =SUM(J6:J7) -> 1056.083 | L8: =SUM(L6:L7) -> 256.959
B10: Employee cost | C10: =-Expenses!C59 -> -4.358 | D10: =-Expenses!D59 -> -9.463 | E10: =-Expenses!E59 -> -9.149439 | F10: =-Expenses!F59 -> -12.102 | G10: =-Expenses!G59 -> -18.768 | H10: =-Expenses!H59 -> -29.476 | I10: =-Expenses!I59 -> -37.608 | J10: -69.633 | L10: -20.384
B11: General and administration expenses | C11: =-Expenses!C106 -> -13.575 | D11: =-Expenses!D106 -> -20.039 | E11: =-Expenses!E106 -> -29.235321 | F11: =-Expenses!F106 -> -28.193 | G11: =-Expenses!G106 -> -28.902 | H11: =-Expenses!H106 -> -54.341 | I11: =-Expenses!I106 -> -98.537 | J11: =-Expenses!J106 -> 0 | L11: =(-Expenses!L106)/10 -> 0
B12: Selling and distribution expenses | C12: =-Expenses!C115 -> -0.727 | D12: =-Expenses!D115 -> -0.465 | E12: =-Expenses!E115 -> -0.900144 | F12: =-Expenses!F115 -> -0.164 | G12: =-Expenses!G115 -> -0.287 | H12: =-Expenses!H115 -> -1.44 | I12: =-Expenses!I115 -> -4.047 | J12: =-Expenses!J115 -> 0 | L12: =(-Expenses!L115)/10 -> 0
B13: Miscellaneous expenses | C13: =-Expenses!C124-Expenses!C126 -> -1.09 | D13: =-Expenses!D124-Expenses!D126 -> -2.981 | E13: =-Expenses!E124-Expenses!E126 -> 0 | F13: =-Expenses!F124-Expenses!F126 -> -0.025 | G13: =-Expenses!G124-Expenses!G126 -> -8.491 | H13: =-Expenses!H124-Expenses!H126 -> -3.134 | I13: =-Expenses!I124-Expenses!I126 -> -8.766 | J13: -204.299 | L13: -37.178
B14: EBITDA | C14: =SUM(C10:C13)+C8 -> 25.539 | D14: =SUM(D10:D13)+D8 -> 43.05 | E14: =SUM(E10:E13)+E8 -> 77.596288 | F14: =SUM(F10:F13)+F8 -> 131.538 | G14: =SUM(G10:G13)+G8 -> 324.152 | H14: =SUM(H10:H13)+H8 -> 686.845 | I14: =SUM(I10:I13)+I8 -> 498.754 | J14: =SUM(J10:J13)+J8 -> 782.151 | L14: =SUM(L10:L13)+L8 -> 199.397
B15: Depreciation and amortisation | C15: =-Expenses!C143 -> -2.062 | D15: =-Expenses!D143 -> -7.994 | E15: =-Expenses!E143 -> -15.135037 | F15: =-Expenses!F143 -> -20.645 | G15: =-Expenses!G143 -> -24.345 | H15: =-Expenses!H143 -> -43.582 | I15: =-Expenses!I143 -> -60.754 | J15: -114.317 | L15: -34.253
B16: EBIT | C16: =SUM(C14:C15) -> 23.477 | D16: =SUM(D14:D15) -> 35.056 | E16: =SUM(E14:E15) -> 62.461251 | F16: =SUM(F14:F15) -> 110.893 | G16: =SUM(G14:G15) -> 299.807 | H16: =SUM(H14:H15) -> 643.263 | I16: =SUM(I14:I15) -> 438 | J16: =SUM(J14:J15) -> 667.834 | L16: =SUM(L14:L15) -> 165.144
B17: Other income | C17: ='Revenue & OI'!C22 -> 0.41 | D17: ='Revenue & OI'!D22 -> 0.28 | E17: ='Revenue & OI'!E22 -> 2.70783 | F17: ='Revenue & OI'!F22 -> 1.336 | G17: ='Revenue & OI'!G22 -> 4.163 | H17: ='Revenue & OI'!H22 -> 13.823 | I17: ='Revenue & OI'!I22 -> 31.257 | J17: 52.019 | L17: 5.585
B18: Interest expenses | C18: =-Expenses!C140 -> -2.114 | D18: =-Expenses!D140 -> -5.288 | E18: =-Expenses!E140 -> -11.922847 | F18: =-Expenses!F140 -> -17.019 | G18: =-Expenses!G140 -> -24.837 | H18: =-Expenses!H140 -> -23.301 | I18: =-Expenses!I140 -> -39.383 | J18: -97.879 | L18: -36.553
B19: Profit before taxation & exceptional items | C19: =C16+C17+C18 -> 21.773 | D19: =D16+D17+D18 -> 30.048 | E19: =E16+E17+E18 -> 53.246234 | F19: =F16+F17+F18 -> 95.21 | G19: =G16+G17+G18 -> 279.133 | H19: =H16+H17+H18 -> 633.785 | I19: =I16+I17+I18 -> 429.874 | J19: =J16+J17+J18 -> 621.974 | L19: =L16+L17+L18 -> 134.176
B20: Other exceptional income | C20: =Expenses!C153+Expenses!C171+Expenses!C174 -> 0 | D20: =Expenses!D153+Expenses!D171+Expenses!D174 -> 0 | E20: =Expenses!E153+Expenses!E171+Expenses!E174 -> 0 | F20: =Expenses!F153+Expenses!F171+Expenses!F174 -> -0.433 | G20: =Expenses!G153+Expenses!G171+Expenses!G174 -> 0 | H20: =Expenses!H153+Expenses!H171+Expenses!H174 -> 0 | I20: =Expenses!I153+Expenses!I171+Expenses!I174 -> 0 | J20: =Expenses!J153+Expenses!J171+Expenses!J174 -> 0 | L20: =Expenses!L153+Expenses!L171+Expenses!L174 -> 0
B21: Profit before taxes | C21: =SUM(C19:C20) -> 21.773 | D21: =SUM(D19:D20) -> 30.048 | E21: =SUM(E19:E20) -> 53.246234 | F21: =SUM(F19:F20) -> 94.777 | G21: =SUM(G19:G20) -> 279.133 | H21: =SUM(H19:H20) -> 633.785 | I21: =SUM(I19:I20) -> 429.874 | J21: =SUM(J19:J20) -> 621.974 | L21: =SUM(L19:L20) -> 134.176
B23: Income tax expense | C23: =-Expenses!C167 -> -7.391 | D23: =-Expenses!D167 -> -2.956 | E23: =-Expenses!E167 -> -10.705073 | F23: =-Expenses!F167 -> -26.457 | G23: =-Expenses!G167 -> -71.4 | H23: =-Expenses!H167 -> -161.791 | I23: =-Expenses!I167 -> -99.845 | J23: =(-1024.07-235.53)/10 -> -125.96 | L23: =(-154.16-79.13)/10 -> -23.329
B24: Net income (pre minority interest) | C24: =C21+C23 -> 14.382 | D24: =D21+D23 -> 27.092 | E24: =E21+E23 -> 42.541161 | F24: =F21+F23 -> 68.32 | G24: =G21+G23 -> 207.733 | H24: =H21+H23 -> 471.994 | I24: =I21+I23 -> 330.029 | J24: =J21+J23 -> 496.014 | L24: =L21+L23 -> 110.847
B25: Minority interest | C25: =Expenses!C172 -> -1.202 | D25: =Expenses!D172 -> -8.076 | E25: =Expenses!E172 -> -2.592405 | F25: =Expenses!F172 -> -1.291 | G25: =Expenses!G172 -> -5.1 | H25: =Expenses!H172 -> -1.534 | I25: =Expenses!I172 -> 0.779 | J25: =Expenses!J172 -> 0 | L25: =Expenses!L172 -> 0
B26: Share of associate | C26: =Expenses!C173 -> 0 | D26: =Expenses!D173 -> 0 | E26: =Expenses!E173 -> -5.405896 | F26: =Expenses!F173 -> -1.788 | G26: =Expenses!G173 -> -8.761 | H26: =Expenses!H173 -> -4.467 | I26: =Expenses!I173 -> -58.368 | J26: =Expenses!J173 -> 0 | L26: =Expenses!L173 -> 0
B27: Net income (post minority interest) | C27: =SUM(C24:C26) -> 13.18 | D27: =SUM(D24:D26) -> 19.016 | E27: =SUM(E24:E26) -> 34.54286 | F27: =SUM(F24:F26) -> 65.241 | G27: =SUM(G24:G26) -> 193.872 | H27: =SUM(H24:H26) -> 465.993 | I27: =SUM(I24:I26) -> 272.44 | J27: =SUM(J24:J26) -> 496.014 | L27: =SUM(L24:L26) -> 110.847
B29: Conversion rate (rs/$) | C29: =+'CF Dashboard'!C32 -> 65.0441 | D29: =+'CF Dashboard'!D32 -> 69.1713 | E29: =+'CF Dashboard'!E32 -> 76.1522 | F29: =+'CF Dashboard'!F32 -> 73.5047 | G29: =+'CF Dashboard'!G32 -> 75.8071 | H29: =+'CF Dashboard'!H32 -> 82.2169 | I29: =+'CF Dashboard'!I32 -> 83.3739 | J29: =+'CF Dashboard'!J32 -> 85.58 | L29: =+'CF Dashboard'!L32 -> 0
B31: Margin indicators
B32: Gross margin | C32: =IF(C6=0,"NA",C8/C6) -> 0.42721844 | D32: =IF(D6=0,"NA",D8/D6) -> 0.71918768 | E32: =IF(E6=0,"NA",E8/E6) -> 0.48886246 | F32: =IF(F6=0,"NA",F8/F6) -> 0.51685886 | G32: =IF(G6=0,"NA",G8/G6) -> 0.62284904 | H32: =IF(H6=0,"NA",H8/H6) -> 0.384676 | I32: =IF(I6=0,"NA",I8/I6) -> 0.39595288 | J32: =IF(J6=0,"NA",J8/J6) -> 0.52618224 | L32: =IF(L6=0,"NA",L8/L6) -> 0.53009108
B33: EBITDA margin | C33: =IF(C6=0,"NA",C14/C6) -> 0.24091351 | D33: =IF(D6=0,"NA",D14/D6) -> 0.40739269 | E33: =IF(E6=0,"NA",E14/E6) -> 0.32455104 | F33: =IF(F6=0,"NA",F14/F6) -> 0.39522027 | G33: =IF(G6=0,"NA",G14/G6) -> 0.53047231 | H33: =IF(H6=0,"NA",H14/H6) -> 0.34081594 | I33: =IF(I6=0,"NA",I14/I6) -> 0.30489335 | J33: =IF(J6=0,"NA",J14/J6) -> 0.3896985 | L33: =IF(L6=0,"NA",L14/L6) -> 0.41134411
B34: Profit before taxes | C34: =IF(C6=0,"NA",C21/C6) -> 0.20538822 | D34: =IF(D6=0,"NA",D21/D6) -> 0.28435158 | E34: =IF(E6=0,"NA",E21/E6) -> 0.22270551 | F34: =IF(F6=0,"NA",F21/F6) -> 0.28476783 | G34: =IF(G6=0,"NA",G21/G6) -> 0.45679905 | H34: =IF(H6=0,"NA",H21/H6) -> 0.3144873 | I34: =IF(I6=0,"NA",I21/I6) -> 0.26278631 | J34: =IF(J6=0,"NA",J21/J6) -> 0.309892 | L34: =IF(L6=0,"NA",L21/L6) -> 0.27679708
B35: Net income margin | C35: =IF(C6=0,"NA",C24/C6) -> 0.13566773 | D35: =IF(D6=0,"NA",D24/D6) -> 0.25637823 | E35: =IF(E6=0,"NA",E24/E6) -> 0.17793091 | F35: =IF(F6=0,"NA",F24/F6) -> 0.20527489 | G35: =IF(G6=0,"NA",G24/G6) -> 0.33995349 | H35: =IF(H6=0,"NA",H24/H6) -> 0.23420579 | I35: =IF(I6=0,"NA",I24/I6) -> 0.20175006 | J35: =IF(J6=0,"NA",J24/J6) -> 0.24713375 | L35: =IF(L6=0,"NA",L24/L6) -> 0.22867074
B37: Growth indicators
B38: Revenue growth | C38: NA | D38: =IF(C6=0,"NA", (D6/ABS(C6)-1)) -> -0.0031789754 | E38: =IF(D6=0,"NA", (E6/ABS(D6)-1)) -> 1.2625491 | F38: =IF(E6=0,"NA", (F6/ABS(E6)-1)) -> 0.3920476 | G38: =IF(F6=0,"NA", (G6/ABS(F6)-1)) -> 0.83600543 | H38: =IF(G6=0,"NA", (H6/ABS(G6)-1)) -> 2.2980167 | I38: =IF(H6=0,"NA", (I6/ABS(H6)-1)) -> -0.18829244 | J38: =IF(I6=0,"NA", (J6/ABS(I6)-1)) -> 0.22694031 | L38: =IF(K6=0,"NA", (L6/ABS(K6)-1)) -> NA
B39: EBITDA growth | C39: NA | D39: =IF(C14=0,"NA", (D14/ABS(C14)-1)) -> 0.68565723 | E39: =IF(D14=0,"NA", (E14/ABS(D14)-1)) -> 0.80246894 | F39: =IF(E14=0,"NA", (F14/ABS(E14)-1)) -> 0.69515841 | G39: =IF(F14=0,"NA", (G14/ABS(F14)-1)) -> 1.4643221 | H39: =IF(G14=0,"NA", (H14/ABS(G14)-1)) -> 1.1188979 | I39: =IF(H14=0,"NA", (I14/ABS(H14)-1)) -> -0.27384781 | J39: =IF(I14=0,"NA", (J14/ABS(I14)-1)) -> 0.56820998 | L39: =IF(K7=0,"NA", (L7/ABS(K7)-1)) -> NA
B40: Profit Before Taxes | C40: NA | D40: =IF(C21=0,"NA", (D21/ABS(C21)-1)) -> 0.38005787 | E40: =IF(D21=0,"NA", (E21/ABS(D21)-1)) -> 0.7720392 | F40: =IF(E21=0,"NA", (F21/ABS(E21)-1)) -> 0.77997565 | G40: =IF(F21=0,"NA", (G21/ABS(F21)-1)) -> 1.9451555 | H40: =IF(G21=0,"NA", (H21/ABS(G21)-1)) -> 1.2705484 | I40: =IF(H21=0,"NA", (I21/ABS(H21)-1)) -> -0.32173529 | J40: =IF(I21=0,"NA", (J21/ABS(I21)-1)) -> 0.44687513 | L40: =IF(K8=0,"NA", (L8/ABS(K8)-1)) -> NA
B41: Net income growth | C41: NA | D41: =IF(C27=0,"NA", (D27/ABS(C27)-1)) -> 0.44279211 | E41: =IF(D27=0,"NA", (E27/ABS(D27)-1)) -> 0.81651557 | F41: =IF(E27=0,"NA", (F27/ABS(E27)-1)) -> 0.88869711 | G41: =IF(F27=0,"NA", (G27/ABS(F27)-1)) -> 1.9716283 | H41: =IF(G27=0,"NA", (H27/ABS(G27)-1)) -> 1.4036117 | I41: =IF(H27=0,"NA", (I27/ABS(H27)-1)) -> -0.41535602 | J41: =IF(I27=0,"NA", (J27/ABS(I27)-1)) -> 0.82063574 | L41: =IF(K9=0,"NA", (L9/ABS(K9)-1)) -> NA

Sheet CF CFS
B1: =+Cover!B3 -> Knowledge Marine & Engineering Works Ltd.
B3: Cash Flow
B4: Rs mm | C4: Mar-18(A) | D4: Mar-19(A) | E4: Mar-20(A) | F4: Mar-21(A) | G4: Mar-22(A) | H4: Mar-23(A) | I4: Mar-24(A) | J4: Mar-25(A)
C5: ='Detailed CFS'!C5 -> Consolidated | D5: ='Detailed CFS'!D5 -> Consolidated | E5: ='Detailed CFS'!E5 -> Consolidated | F5: ='Detailed CFS'!F5 -> Consolidated | G5: ='Detailed CFS'!G5 -> Consolidated | H5: ='Detailed CFS'!H5 -> Consolidated | I5: ='Detailed CFS'!I5 -> Consolidated | J5: =I5 -> Consolidated
B6: Profit before tax | C6: ='Detailed CFS'!C6 -> 21.773 | D6: ='Detailed CFS'!D6 -> 30.048 | E6: ='Detailed CFS'!E6 -> 53.246233 | F6: ='Detailed CFS'!F6 -> 94.777 | G6: ='Detailed CFS'!G6 -> 280.078 | H6: ='Detailed CFS'!H6 -> 633.784 | I6: ='Detailed CFS'!I6 -> 429.874 | J6: ='Detailed CFS'!J6 -> 0
B7: Depreciation & amortization | C7: ='Detailed CFS'!C7+'Detailed CFS'!C8 -> 2.062 | D7: ='Detailed CFS'!D7+'Detailed CFS'!D8 -> 7.994 | E7: ='Detailed CFS'!E7+'Detailed CFS'!E8 -> 15.135037 | F7: ='Detailed CFS'!F7+'Detailed CFS'!F8 -> 20.645 | G7: ='Detailed CFS'!G7+'Detailed CFS'!G8 -> 24.345 | H7: ='Detailed CFS'!H7+'Detailed CFS'!H8 -> 43.582 | I7: ='Detailed CFS'!I7+'Detailed CFS'!I8 -> 60.754 | J7: ='Detailed CFS'!J7+'Detailed CFS'!J8 -> 0
B8: Interest expenses | C8: ='Detailed CFS'!C9 -> 1.917 | D8: ='Detailed CFS'!D9 -> 5.099 | E8: ='Detailed CFS'!E9 -> 11.109093 | F8: ='Detailed CFS'!F9 -> 17.019 | G8: ='Detailed CFS'!G9 -> 24.837 | H8: ='Detailed CFS'!H9 -> 23.301 | I8: ='Detailed CFS'!I9 -> 39.383 | J8: ='Detailed CFS'!J9 -> 0
B9: Interest income | C9: ='Detailed CFS'!C13 -> -0.41 | D9: ='Detailed CFS'!D13 -> -0.28 | E9: ='Detailed CFS'!E13 -> -0.895735 | F9: ='Detailed CFS'!F13 -> -1.2 | G9: ='Detailed CFS'!G13 -> -3.645 | H9: ='Detailed CFS'!H13 -> -13.804 | I9: ='Detailed CFS'!I13 -> -31.221 | J9: ='Detailed CFS'!J13 -> 0
B10: Profit/loss on sale of fixed assets | C10: ='Detailed CFS'!C10 -> 0 | D10: ='Detailed CFS'!D10 -> 0 | E10: ='Detailed CFS'!E10 -> 0 | F10: ='Detailed CFS'!F10 -> 0 | G10: ='Detailed CFS'!G10 -> 0 | H10: ='Detailed CFS'!H10 -> 0 | I10: ='Detailed CFS'!I10 -> 0 | J10: ='Detailed CFS'!J10 -> 0
B11: Provision & written off | C11: ='Detailed CFS'!C18+'Detailed CFS'!C23 -> 0 | D11: ='Detailed CFS'!D18+'Detailed CFS'!D23 -> 3.143 | E11: ='Detailed CFS'!E18+'Detailed CFS'!E23 -> 0 | F11: ='Detailed CFS'!F18+'Detailed CFS'!F23 -> 0.493 | G11: ='Detailed CFS'!G18+'Detailed CFS'!G23 -> 0.454 | H11: ='Detailed CFS'!H18+'Detailed CFS'!H23 -> -0.017 | I11: ='Detailed CFS'!I18+'Detailed CFS'!I23 -> 0 | J11: ='Detailed CFS'!J18+'Detailed CFS'!J23 -> 0
B12: Other adjustments | C12: ='Detailed CFS'!C11+'Detailed CFS'!C12+'Detailed CFS'!C14+'Detailed CFS'!C15+'Detailed CFS'!C16+'Detailed CFS'!C17+'Detailed CFS'!C19+'Detailed CFS'!C20+'Detailed CFS'!C21+'Detailed CFS'!C22+'Detailed CFS'!C24+'Detailed CFS'!C25 -> 0 | D12: ='Detailed CFS'!D11+'Detailed CFS'!D12+'Detailed CFS'!D14+'Detailed CFS'!D15+'Detailed CFS'!D16+'Detailed CFS'!D17+'Detailed CFS'!D19+'Detailed CFS'!D20+'Detailed CFS'!D21+'Detailed CFS'!D22+'Detailed CFS'!D24+'Detailed CFS'!D25 -> 0 | E12: ='Detailed CFS'!E11+'Detailed CFS'!E12+'Detailed CFS'!E14+'Detailed CFS'!E15+'Detailed CFS'!E16+'Detailed CFS'!E17+'Detailed CFS'!E19+'Detailed CFS'!E20+'Detailed CFS'!E21+'Detailed CFS'!E22+'Detailed CFS'!E24+'Detailed CFS'!E25 -> 0 | F12: ='Detailed CFS'!F11+'Detailed CFS'!F12+'Detailed CFS'!F14+'Detailed CFS'!F15+'Detailed CFS'!F16+'Detailed CFS'!F17+'Detailed CFS'!F19+'Detailed CFS'!F20+'Detailed CFS'!F21+'Detailed CFS'!F22+'Detailed CFS'!F24+'Detailed CFS'!F25 -> 0 | G12: ='Detailed CFS'!G11+'Detailed CFS'!G12+'Detailed CFS'!G14+'Detailed CFS'!G15+'Detailed CFS'!G16+'Detailed CFS'!G17+'Detailed CFS'!G19+'Detailed CFS'!G20+'Detailed CFS'!G21+'Detailed CFS'!G22+'Detailed CFS'!G24+'Detailed CFS'!G25 -> 0 | H12: ='Detailed CFS'!H11+'Detailed CFS'!H12+'Detailed CFS'!H14+'Detailed CFS'!H15+'Detailed CFS'!H16+'Detailed CFS'!H17+'Detailed CFS'!H19+'Detailed CFS'!H20+'Detailed CFS'!H21+'Detailed CFS'!H22+'Detailed CFS'!H24+'Detailed CFS'!H25 -> 0.5 | I12: ='Detailed CFS'!I11+'Detailed CFS'!I12+'Detailed CFS'!I14+'Detailed CFS'!I15+'Detailed CFS'!I16+'Detailed CFS'!I17+'Detailed CFS'!I19+'Detailed CFS'!I20+'Detailed CFS'!I21+'Detailed CFS'!I22+'Detailed CFS'!I24+'Detailed CFS'!I25 -> 2.236 | J12: ='Detailed CFS'!J11+'Detailed CFS'!J12+'Detailed CFS'!J14+'Detailed CFS'!J15+'Detailed CFS'!J16+'Detailed CFS'!J17+'Detailed CFS'!J19+'Detailed CFS'!J20+'Detailed CFS'!J21+'Detailed CFS'!J22+'Detailed CFS'!J24+'Detailed CFS'!J25 -> 0
B13: Tax paid | C13: ='Detailed CFS'!C42+'Detailed CFS'!C43+'Detailed CFS'!C44+'Detailed CFS'!C45 -> -3.707 | D13: ='Detailed CFS'!D42+'Detailed CFS'!D43+'Detailed CFS'!D44+'Detailed CFS'!D45 -> -2.998 | E13: ='Detailed CFS'!E42+'Detailed CFS'!E43+'Detailed CFS'!E44+'Detailed CFS'!E45 -> -4.916059 | F13: ='Detailed CFS'!F42+'Detailed CFS'!F43+'Detailed CFS'!F44+'Detailed CFS'!F45 -> -18.539 | G13: ='Detailed CFS'!G42+'Detailed CFS'!G43+'Detailed CFS'!G44+'Detailed CFS'!G45 -> -62.262 | H13: ='Detailed CFS'!H42+'Detailed CFS'!H43+'Detailed CFS'!H44+'Detailed CFS'!H45 -> -148.708 | I13: ='Detailed CFS'!I42+'Detailed CFS'!I43+'Detailed CFS'!I44+'Detailed CFS'!I45 -> -88.119 | J13: ='Detailed CFS'!J42+'Detailed CFS'!J43+'Detailed CFS'!J44+'Detailed CFS'!J45 -> 0
B14: Cash from operating activities (before change in wc) | C14: =SUM(C6:C13) -> 21.635 | D14: =SUM(D6:D13) -> 43.006 | E14: =SUM(E6:E13) -> 73.678569 | F14: =SUM(F6:F13) -> 113.195 | G14: =SUM(G6:G13) -> 263.807 | H14: =SUM(H6:H13) -> 538.638 | I14: =SUM(I6:I13) -> 412.907 | J14: =SUM(J6:J13) -> 0
B15: (increase)/decrease in accounts receivable | C15: ='Detailed CFS'!C28 -> -10.29 | D15: ='Detailed CFS'!D28 -> 6.203 | E15: ='Detailed CFS'!E28 -> 27.398893 | F15: ='Detailed CFS'!F28 -> 26.327 | G15: ='Detailed CFS'!G28 -> -35.459 | H15: ='Detailed CFS'!H28 -> -519.059 | I15: ='Detailed CFS'!I28 -> 123.727 | J15: ='Detailed CFS'!J28 -> 0
B16: (increase)/decrease in inventories | C16: ='Detailed CFS'!C29 -> 0 | D16: ='Detailed CFS'!D29 -> 0 | E16: ='Detailed CFS'!E29 -> 0 | F16: ='Detailed CFS'!F29 -> -0.603 | G16: ='Detailed CFS'!G29 -> 1.41 | H16: ='Detailed CFS'!H29 -> -9.538 | I16: ='Detailed CFS'!I29 -> -0.74 | J16: ='Detailed CFS'!J29 -> 0
B17: (increase)/decrease in other current assets | C17: ='Detailed CFS'!C30+'Detailed CFS'!C31+'Detailed CFS'!C33+'Detailed CFS'!C34+'Detailed CFS'!C37 -> -3.723 | D17: ='Detailed CFS'!D30+'Detailed CFS'!D31+'Detailed CFS'!D33+'Detailed CFS'!D34+'Detailed CFS'!D37 -> -8.589 | E17: ='Detailed CFS'!E30+'Detailed CFS'!E31+'Detailed CFS'!E33+'Detailed CFS'!E34+'Detailed CFS'!E37 -> -38.700599 | F17: ='Detailed CFS'!F30+'Detailed CFS'!F31+'Detailed CFS'!F33+'Detailed CFS'!F34+'Detailed CFS'!F37 -> -59.865 | G17: ='Detailed CFS'!G30+'Detailed CFS'!G31+'Detailed CFS'!G33+'Detailed CFS'!G34+'Detailed CFS'!G37 -> 2.546 | H17: ='Detailed CFS'!H30+'Detailed CFS'!H31+'Detailed CFS'!H33+'Detailed CFS'!H34+'Detailed CFS'!H37 -> -91.958 | I17: ='Detailed CFS'!I30+'Detailed CFS'!I31+'Detailed CFS'!I33+'Detailed CFS'!I34+'Detailed CFS'!I37 -> 14.659 | J17: ='Detailed CFS'!J30+'Detailed CFS'!J31+'Detailed CFS'!J33+'Detailed CFS'!J34+'Detailed CFS'!J37 -> 0
B18: Increase/(decrease) in accounts payable | C18: ='Detailed CFS'!C32 -> 22.577 | D18: ='Detailed CFS'!D32 -> 71.561 | E18: ='Detailed CFS'!E32 -> -42.690545 | F18: ='Detailed CFS'!F32 -> -30.766 | G18: ='Detailed CFS'!G32 -> 113.614 | H18: ='Detailed CFS'!H32 -> 293.407 | I18: ='Detailed CFS'!I32 -> -206.841 | J18: ='Detailed CFS'!J32 -> 0
B19: Increase/(decrease) in other current liability | C19: ='Detailed CFS'!C35+'Detailed CFS'!C36 -> 0 | D19: ='Detailed CFS'!D35+'Detailed CFS'!D36 -> 0 | E19: ='Detailed CFS'!E35+'Detailed CFS'!E36 -> 0 | F19: ='Detailed CFS'!F35+'Detailed CFS'!F36 -> 0 | G19: ='Detailed CFS'!G35+'Detailed CFS'!G36 -> 0 | H19: ='Detailed CFS'!H35+'Detailed CFS'!H36 -> 0.69 | I19: ='Detailed CFS'!I35+'Detailed CFS'!I36 -> 0.495 | J19: ='Detailed CFS'!J35+'Detailed CFS'!J36 -> 0
B20: Cash from operating activities | C20: =SUM(C14:C19) -> 30.199 | D20: =SUM(D14:D19) -> 112.181 | E20: =SUM(E14:E19) -> 19.686318 | F20: =SUM(F14:F19) -> 48.288 | G20: =SUM(G14:G19) -> 345.918 | H20: =SUM(H14:H19) -> 212.18 | I20: =SUM(I14:I19) -> 344.207 | J20: 578.393
B22: Capital expenditure (maintenance) | C22: 0 | D22: 0 | E22: 0 | F22: 0 | G22: 0 | H22: 0 | I22: 0 | J22: 0
B23: Capital expenditure (expansion) | C23: ='Detailed CFS'!C48 -> -109.967 | D23: ='Detailed CFS'!D48 -> -96.066 | E23: ='Detailed CFS'!E48 -> -165.89582 | F23: ='Detailed CFS'!F48 -> -25.535 | G23: ='Detailed CFS'!G48 -> -290.822 | H23: ='Detailed CFS'!H48 -> -178.433 | I23: ='Detailed CFS'!I48 -> -621.928 | J23: ='Detailed CFS'!J48 -> 0
B24: Sale of fixed assets | C24: ='Detailed CFS'!C49 -> 0 | D24: ='Detailed CFS'!D49 -> 1.25 | E24: ='Detailed CFS'!E49 -> 0 | F24: ='Detailed CFS'!F49 -> 11.393 | G24: ='Detailed CFS'!G49 -> 0 | H24: ='Detailed CFS'!H49 -> 0 | I24: ='Detailed CFS'!I49 -> 0 | J24: ='Detailed CFS'!J49 -> 0
B25: Investment in subsidiaries | C25: ='Detailed CFS'!C52+'Detailed CFS'!C53+'Detailed CFS'!C54 -> 5.795 | D25: ='Detailed CFS'!D52+'Detailed CFS'!D53+'Detailed CFS'!D54 -> 0 | E25: ='Detailed CFS'!E52+'Detailed CFS'!E53+'Detailed CFS'!E54 -> -1.630915 | F25: ='Detailed CFS'!F52+'Detailed CFS'!F53+'Detailed CFS'!F54 -> 0 | G25: ='Detailed CFS'!G52+'Detailed CFS'!G53+'Detailed CFS'!G54 -> 0 | H25: ='Detailed CFS'!H52+'Detailed CFS'!H53+'Detailed CFS'!H54 -> 0 | I25: ='Detailed CFS'!I52+'Detailed CFS'!I53+'Detailed CFS'!I54 -> 0 | J25: ='Detailed CFS'!J52+'Detailed CFS'!J53+'Detailed CFS'!J54 -> 0
B26: Interest received | C26: ='Detailed CFS'!C56 -> 0.41 | D26: ='Detailed CFS'!D56 -> 0.28 | E26: ='Detailed CFS'!E56 -> 0 | F26: ='Detailed CFS'!F56 -> 1.18 | G26: ='Detailed CFS'!G56 -> 3.645 | H26: ='Detailed CFS'!H56 -> 13.804 | I26: ='Detailed CFS'!I56 -> 31.221 | J26: ='Detailed CFS'!J56 -> 0
B27: Dividend income | C27: ='Detailed CFS'!C55 -> 0 | D27: ='Detailed CFS'!D55 -> 0 | E27: ='Detailed CFS'!E55 -> 0 | F27: ='Detailed CFS'!F55 -> 0 | G27: ='Detailed CFS'!G55 -> 0 | H27: ='Detailed CFS'!H55 -> 0 | I27: ='Detailed CFS'!I55 -> 0 | J27: ='Detailed CFS'!J55 -> 0
B28: Other investment activities | C28: ='Detailed CFS'!C50+'Detailed CFS'!C51+'Detailed CFS'!C57+'Detailed CFS'!C58+'Detailed CFS'!C59+'Detailed CFS'!C60+'Detailed CFS'!C61 -> 0 | D28: ='Detailed CFS'!D50+'Detailed CFS'!D51+'Detailed CFS'!D57+'Detailed CFS'!D58+'Detailed CFS'!D59+'Detailed CFS'!D60+'Detailed CFS'!D61 -> 0 | E28: ='Detailed CFS'!E50+'Detailed CFS'!E51+'Detailed CFS'!E57+'Detailed CFS'!E58+'Detailed CFS'!E59+'Detailed CFS'!E60+'Detailed CFS'!E61 -> 75.286291 | F28: ='Detailed CFS'!F50+'Detailed CFS'!F51+'Detailed CFS'!F57+'Detailed CFS'!F58+'Detailed CFS'!F59+'Detailed CFS'!F60+'Detailed CFS'!F61 -> -28.536 | G28: ='Detailed CFS'!G50+'Detailed CFS'!G51+'Detailed CFS'!G57+'Detailed CFS'!G58+'Detailed CFS'!G59+'Detailed CFS'!G60+'Detailed CFS'!G61 -> -18.08 | H28: ='Detailed CFS'!H50+'Detailed CFS'!H51+'Detailed CFS'!H57+'Detailed CFS'!H58+'Detailed CFS'!H59+'Detailed CFS'!H60+'Detailed CFS'!H61 -> -62.905 | I28: ='Detailed CFS'!I50+'Detailed CFS'!I51+'Detailed CFS'!I57+'Detailed CFS'!I58+'Detailed CFS'!I59+'Detailed CFS'!I60+'Detailed CFS'!I61 -> -128.852 | J28: ='Detailed CFS'!J50+'Detailed CFS'!J51+'Detailed CFS'!J57+'Detailed CFS'!J58+'Detailed CFS'!J59+'Detailed CFS'!J60+'Detailed CFS'!J61 -> 0
B29: Cash from investing activities | C29: =SUM(C22:C28) -> -103.762 | D29: =SUM(D22:D28) -> -94.536 | E29: =SUM(E22:E28) -> -92.240448 | F29: =SUM(F22:F28) -> -41.498 | G29: =SUM(G22:G28) -> -305.257 | H29: =SUM(H22:H28) -> -227.534 | I29: =SUM(I22:I28) -> -719.559 | J29: -1269.627
B31: Proceeds from long term borrowings | C31: ='Detailed CFS'!C65 -> 0 | D31: ='Detailed CFS'!D65 -> 30.94 | E31: ='Detailed CFS'!E65 -> 0 | F31: ='Detailed CFS'!F65 -> 0 | G31: ='Detailed CFS'!G65 -> 55.405 | H31: ='Detailed CFS'!H65 -> 0 | I31: ='Detailed CFS'!I65 -> 375.421 | J31: ='Detailed CFS'!J65 -> 0
B32: Repayment of long term borrowings | C32: ='Detailed CFS'!C66 -> 0 | D32: ='Detailed CFS'!D66 -> 0 | E32: ='Detailed CFS'!E66 -> 0 | F32: ='Detailed CFS'!F66 -> 0 | G32: ='Detailed CFS'!G66 -> 0 | H32: ='Detailed CFS'!H66 -> -129.699 | I32: ='Detailed CFS'!I66 -> 0 | J32: ='Detailed CFS'!J66 -> 0
B33: Increase / (decrease) in short term borrowing | C33: ='Detailed CFS'!C64+'Detailed CFS'!C79 -> 67.378 | D33: ='Detailed CFS'!D64+'Detailed CFS'!D79 -> 0 | E33: ='Detailed CFS'!E64+'Detailed CFS'!E79 -> 73.373662 | F33: ='Detailed CFS'!F64+'Detailed CFS'!F79 -> 0 | G33: ='Detailed CFS'!G64+'Detailed CFS'!G79 -> 0 | H33: ='Detailed CFS'!H64+'Detailed CFS'!H79 -> 0 | I33: ='Detailed CFS'!I64+'Detailed CFS'!I79 -> 0 | J33: ='Detailed CFS'!J64+'Detailed CFS'!J79 -> 0
B34: Proceeds from shares warrants | C34: ='Detailed CFS'!C73 -> 0 | D34: ='Detailed CFS'!D73 -> 0 | E34: ='Detailed CFS'!E73 -> 0 | F34: ='Detailed CFS'!F73 -> 0 | G34: ='Detailed CFS'!G73 -> 0 | H34: ='Detailed CFS'!H73 -> 0 | I34: ='Detailed CFS'!I73 -> 0 | J34: ='Detailed CFS'!J73 -> 0
B35: Proceeds from issue of equity share capital | C35: ='Detailed CFS'!C74+'Detailed CFS'!C75 -> 0 | D35: ='Detailed CFS'!D74+'Detailed CFS'!D75 -> 24.9 | E35: ='Detailed CFS'!E74+'Detailed CFS'!E75 -> 0 | F35: ='Detailed CFS'!F74+'Detailed CFS'!F75 -> 101.232 | G35: ='Detailed CFS'!G74+'Detailed CFS'!G75 -> 0 | H35: ='Detailed CFS'!H74+'Detailed CFS'!H75 -> 395.5 | I35: ='Detailed CFS'!I74+'Detailed CFS'!I75 -> 0.23 | J35: ='Detailed CFS'!J74+'Detailed CFS'!J75 -> 0
B36: Dividends paid | C36: ='Detailed CFS'!C76 -> 0 | D36: ='Detailed CFS'!D76 -> 0 | E36: ='Detailed CFS'!E76 -> 0 | F36: ='Detailed CFS'!F76 -> 0 | G36: ='Detailed CFS'!G76 -> 0 | H36: ='Detailed CFS'!H76 -> 0 | I36: ='Detailed CFS'!I76 -> 0 | J36: ='Detailed CFS'!J76 -> 0
B37: Interest paid | C37: ='Detailed CFS'!C78 -> -1.917 | D37: ='Detailed CFS'!D78 -> -5.099 | E37: ='Detailed CFS'!E78 -> -11.109093 | F37: ='Detailed CFS'!F78 -> -17.019 | G37: ='Detailed CFS'!G78 -> -24.837 | H37: ='Detailed CFS'!H78 -> -23.301 | I37: ='Detailed CFS'!I78 -> -39.383 | J37: ='Detailed CFS'!J78 -> 0
B38: Other financing activities | C38: ='Detailed CFS'!C67+'Detailed CFS'!C68+'Detailed CFS'!C69+'Detailed CFS'!C70+'Detailed CFS'!C71+'Detailed CFS'!C72+'Detailed CFS'!C77+'Detailed CFS'!C80+'Detailed CFS'!C81+'Detailed CFS'!C82+'Detailed CFS'!C83+'Detailed CFS'!C84 -> 7.53 | D38: ='Detailed CFS'!D67+'Detailed CFS'!D68+'Detailed CFS'!D69+'Detailed CFS'!D70+'Detailed CFS'!D71+'Detailed CFS'!D72+'Detailed CFS'!D77+'Detailed CFS'!D80+'Detailed CFS'!D81+'Detailed CFS'!D82+'Detailed CFS'!D83+'Detailed CFS'!D84 -> 4.066 | E38: ='Detailed CFS'!E67+'Detailed CFS'!E68+'Detailed CFS'!E69+'Detailed CFS'!E70+'Detailed CFS'!E71+'Detailed CFS'!E72+'Detailed CFS'!E77+'Detailed CFS'!E80+'Detailed CFS'!E81+'Detailed CFS'!E82+'Detailed CFS'!E83+'Detailed CFS'!E84 -> -45.025663 | F38: ='Detailed CFS'!F67+'Detailed CFS'!F68+'Detailed CFS'!F69+'Detailed CFS'!F70+'Detailed CFS'!F71+'Detailed CFS'!F72+'Detailed CFS'!F77+'Detailed CFS'!F80+'Detailed CFS'!F81+'Detailed CFS'!F82+'Detailed CFS'!F83+'Detailed CFS'!F84 -> 8.097 | G38: ='Detailed CFS'!G67+'Detailed CFS'!G68+'Detailed CFS'!G69+'Detailed CFS'!G70+'Detailed CFS'!G71+'Detailed CFS'!G72+'Detailed CFS'!G77+'Detailed CFS'!G80+'Detailed CFS'!G81+'Detailed CFS'!G82+'Detailed CFS'!G83+'Detailed CFS'!G84 -> 39.148 | H38: ='Detailed CFS'!H67+'Detailed CFS'!H68+'Detailed CFS'!H69+'Detailed CFS'!H70+'Detailed CFS'!H71+'Detailed CFS'!H72+'Detailed CFS'!H77+'Detailed CFS'!H80+'Detailed CFS'!H81+'Detailed CFS'!H82+'Detailed CFS'!H83+'Detailed CFS'!H84 -> 107.068 | I38: ='Detailed CFS'!I67+'Detailed CFS'!I68+'Detailed CFS'!I69+'Detailed CFS'!I70+'Detailed CFS'!I71+'Detailed CFS'!I72+'Detailed CFS'!I77+'Detailed CFS'!I80+'Detailed CFS'!I81+'Detailed CFS'!I82+'Detailed CFS'!I83+'Detailed CFS'!I84 -> -14.829 | J38: ='Detailed CFS'!J67+'Detailed CFS'!J68+'Detailed CFS'!J69+'Detailed CFS'!J70+'Detailed CFS'!J71+'Detailed CFS'!J72+'Detailed CFS'!J77+'Detailed CFS'!J80+'Detailed CFS'!J81+'Detailed CFS'!J82+'Detailed CFS'!J83+'Detailed CFS'!J84 -> 0
B39: Cash from financing activities | C39: =SUM(C31:C38) -> 72.991 | D39: =SUM(D31:D38) -> 54.807 | E39: =SUM(E31:E38) -> 17.238906 | F39: =SUM(F31:F38) -> 92.31 | G39: =SUM(G31:G38) -> 69.716 | H39: =SUM(H31:H38) -> 349.568 | I39: =SUM(I31:I38) -> 321.439 | J39: 634.973
B40: Net cash inflow / outflow | C40: =C20+C29+C39 -> -0.572 | D40: =D20+D29+D39 -> 72.452 | E40: =E20+E29+E39 -> -55.315224 | F40: =F20+F29+F39 -> 99.1 | G40: =G20+G29+G39 -> 110.377 | H40: =H20+H29+H39 -> 334.214 | I40: =I20+I29+I39 -> -53.913 | J40: =J20+J29+J39 -> -56.261
B42: Free cash flow¹ | C42: =C20+C22-C8 -> 28.282 | D42: =D20+D22-D8 -> 107.082 | E42: =E20+E22-E8 -> 8.577225 | F42: =F20+F22-F8 -> 31.269 | G42: =G20+G22-G8 -> 321.081 | H42: =H20+H22-H8 -> 188.879 | I42: =I20+I22-I8 -> 304.824 | J42: =J20+J22-J8 -> 578.393
B44: Conversion rate (rs/$) | C44: =+'CF Dashboard'!C32 -> 65.0441 | D44: =+'CF Dashboard'!D32 -> 69.1713 | E44: =+'CF Dashboard'!E32 -> 76.1522 | F44: =+'CF Dashboard'!F32 -> 73.5047 | G44: =+'CF Dashboard'!G32 -> 75.8071 | H44: =+'CF Dashboard'!H32 -> 82.2169 | I44: =+'CF Dashboard'!I32 -> 83.3739 | J44: =+'CF Dashboard'!J32 -> 85.58
B45: ¹ free cash flow = cash flow from operations (less) interest expense (less) maintenance capex
B47: Opening | D47: =+C48 -> 1.753 | E47: =+D48 -> 74.203 | F47: =+E48 -> 16.213161 | G47: =+F48 -> 115.312 | H47: =+G48 -> 225.691 | I47: =+H48 -> 559.904 | J47: =+I48 -> 505.992
B48: Closing | C48: =+'CF BS'!C38 -> 1.753 | D48: =+'CF BS'!D38 -> 74.203 | E48: =+'CF BS'!E38 -> 16.213161 | F48: =+'CF BS'!F38 -> 115.312 | G48: =+'CF BS'!G38 -> 225.691 | H48: =+'CF BS'!H38 -> 559.904 | I48: =+'CF BS'!I38 -> 505.992 | J48: =+'CF BS'!J38 -> 449.731
B49: Movement | C49: =+C48-C47 -> 1.753 | D49: =+D48-D47 -> 72.45 | E49: =+E48-E47 -> -57.989839 | F49: =+F48-F47 -> 99.098839 | G49: =+G48-G47 -> 110.379 | H49: =+H48-H47 -> 334.213 | I49: =+I48-I47 -> -53.912 | J49: =+J48-J47 -> -56.261
B51: Check | C51: =+C49-C40 -> 2.325 | D51: =+D49-D40 -> -0.002 | E51: =+E49-E40 -> -2.674615 | F51: =+F49-F40 -> -0.001161 | G51: =+G49-G40 -> 0.002 | H51: =+H49-H40 -> -0.001 | I51: =+I49-I40 -> 0.001 | J51: =+J49-J40 -> -1.1368684e-13

Sheet Equity & reserves
B1: =+Cover!B3 -> Knowledge Marine & Engineering Works Ltd.
B3: Equity and reserves
B4: Rs mm | C4: Mar-18(A) | D4: Mar-19(A) | E4: Mar-20(A) | F4: Mar-21(A) | G4: Mar-22(A) | H4: Mar-23(A) | I4: Mar-24(A)
C5: Consolidated | D5: Consolidated | E5: Consolidated | F5: Consolidated | G5: Consolidated | H5: Consolidated | I5: Consolidated
B6: Equity and liabilities
B7: Equity - authorised | C7: 5 | D7: 25 | E7: 40 | F7: 105 | G7: 105 | H7: 110 | I7: 110
B8: Equity - issued | C8: 0.1 | D8: 25 | E8: 25 | F8: 102.36 | G8: 102.36 | H8: 108.01 | I8: 108.01
B9: Equity - subscribed | C9: 0.1 | D9: 25 | E9: 25 | F9: 102.36 | G9: 102.36 | H9: 108.01 | I9: 108.01
B10: Equity - called up | C10: 0.1 | D10: 25 | E10: 25 | F10: 102.36 | G10: 102.36 | H10: 108.01 | I10: 108.01
B11: Less : calls in arrears
B12: Equity paid up | C12: 0.1 | D12: 25 | E12: 25 | F12: 102.36 | G12: 102.36 | H12: 108.01 | I12: 108.01
B13: Equity shares forfeited
B14: Adjustments to equity
B15: Preference capital paid up | C15: =C17+C18 -> 0 | D15: =D17+D18 -> 0 | E15: =E17+E18 -> 0 | F15: =F17+F18 -> 0 | G15: =G17+G18 -> 0 | H15: =H17+H18 -> 0 | I15: =I17+I18 -> 0
B16: Convertible pref. shares
B17: Non - convertible pref. shares
B18: Unclassified shares paid up
B19: Face value | C19: 10 | D19: 10 | E19: 10 | F19: 10 | G19: 10 | H19: 10 | I19: 10
B20: Share capital | C20: =SUM(C12:C15,C18) -> 0.1 | D20: =SUM(D12:D15,D18) -> 25 | E20: =SUM(E12:E15,E18) -> 25 | F20: =SUM(F12:F15,F18) -> 102.36 | G20: =SUM(G12:G15,G18) -> 102.36 | H20: =SUM(H12:H15,H18) -> 108.01 | I20: =SUM(I12:I15,I18) -> 108.01
B22: Share warrants & outstandings | C22: 0 | D22: 0 | E22: 0 | F22: 0 | G22: 0 | H22: 0 | I22: 0
B24: Securities premium | F24: 73.872 | G24: 73.872 | H24: 463.722 | I24: 463.722
B25: Capital reserves
B26: Profit & loss account balance | C26: 20.239 | D26: 39.256 | E26: 62.897733 | F26: 77.275 | G26: 272.092 | H26: 738.085 | I26: 1010.631
B27: General reserves
B28: Investment fluctuation reserve
B29: Govt. grant
B30: Debenture redemption reserve
B31: Capital redemption reserve
B32: Amalgamation reserve
B33: Exchange fluctuation reserve
B34: Statutory reserves
B35: Special reserve
B36: Investment allowance (utilised) reserve
B37: Doubtful debts reserve
B38: Deferred tax reserve
... B44: Minority reserve
B45: Other reserves | E45: 16.334672 | F45: 16.562 | G45: 25.323 | H45: 30.203 | I45: 88.562
B46: Hedging reserve
B47: Reserve excluding revaluation reserve | C47: 20.239 | D47: 39.256 | E47: 79.232405 | F47: 167.709 | G47: 371.287 | H47: 1232.01 | I47: 1562.915
B48: Revaluation reserve - assets
B49: Revaluation reserve - investment
B50: Revaluation reserve | C50: =SUM(C48:C49) -> 0 | D50: =SUM(D48:D49) -> 0 | E50: =SUM(E48:E49) -> 0 | F50: =SUM(F48:F49) -> 0 | G50: =SUM(G48:G49) -> 0 | H50: =SUM(H48:H49) -> 0 | I50: =SUM(I48:I49) -> 0
B51: Total reserves | C51: =SUM(C24:C46,C50) -> 20.239 | D51: =SUM(D24:D46,D50) -> 39.256 | E51: =SUM(E24:E46,E50) -> 79.232405 | F51: =SUM(F24:F46,F50) -> 167.709 | G51: =SUM(G24:G46,G50) -> 371.287 | H51: =SUM(H24:H46,H50) -> 1232.01 | I51: =SUM(I24:I46,I50) -> 1562.915
B53: Shareholder's funds | C53: =C20+C22+C51 -> 20.339 | D53: =D20+D22+D51 -> 64.256 | E53: =E20+E22+E51 -> 104.2324 | F53: =F20+F22+F51 -> 270.069 | G53: =G20+G22+G51 -> 473.647 | H53: =H20+H22+H51 -> 1340.02 | I53: =I20+I22+I51 -> 1670.925
B55: Minority interest | C55: 8.732 | D55: 16.807 | E55: 19.425947 | F55: 19.142 | G55: 24.242 | H55: 26.189 | I55: 25.644

Sheet Borrowings
B1: =+Cover!B3 -> Knowledge Marine & Engineering Works Ltd.
B3: Borrowings
B4: Rs mm | C4: Mar-18(A) | D4: Mar-19(A) | E4: Mar-20(A) | F4: Mar-21(A) | G4: Mar-22(A) | H4: Mar-23(A) | I4: Mar-24(A)
C5: Consolidated | D5: Consolidated | E5: Consolidated | F5: Consolidated | G5: Consolidated | H5: Consolidated | I5: Consolidated
B6: Long-term borrowings
B8: Non convertible debentures
B9: Converible debentures & bonds
B10: Packing credit - bank
B11: Cash credit - bank
B12: Overdrafts - bank
B13: Inter corporate & security deposit
B14: Rupee loan | C14: 23.623 | D14: 63.769 | E14: 82.453738 | F14: 116.353 | G14: 171.758 | H14: 42.058 | I14: 417.48
B15: Foreign currency loan
B17: Term loans - banks | C17: =SUM(C14:C15) -> 23.623 | D17: =SUM(D14:D15) -> 63.769 | E17: =SUM(E14:E15) -> 82.453738 | F17: =SUM(F14:F15) -> 116.353 | G17: =SUM(G14:G15) -> 171.758 | H17: =SUM(H14:H15) -> 42.058 | I17: =SUM(I14:I15) -> 417.48
B18: Rupee loan
B19: Foreign currency loan
B20: Term loans - institutions | C20: =SUM(C18:C19) -> 0 | D20: =SUM(D18:D19) -> 0 | E20: =SUM(E18:E19) -> 0 | F20: =SUM(F18:F19) -> 0 | G20: =SUM(G18:G19) -> 0 | H20: =SUM(H18:H19) -> 0 | I20: =SUM(I18:I19) -> 0
B22: Rupee loan
B23: Foreign currency loan
B24: Working capital loans - bank | C24: =SUM(C22:C23) -> 0 | D24: =SUM(D22:D23) -> 0 | E24: =SUM(E22:E23) -> 0 | F24: =SUM(F22:F23) -> 0 | G24: =SUM(G22:G23) -> 0 | H24: =SUM(H22:H23) -> 0 | I24: =SUM(I22:I23) -> 0
B26: Rupee loan
B27: Foreign currency loan
B28: Bridge loan | C28: =SUM(C26:C27) -> 0 | D28: =SUM(D26:D27) -> 0 | E28: =SUM(E26:E27) -> 0 | F28: =SUM(F26:F27) -> 0 | G28: =SUM(G26:G27) -> 0 | H28: =SUM(H26:H27) -> 0 | I28: =SUM(I26:I27) -> 0
B30: Buyers credit - rupee loans
B31: Buyers credit - foreign loans
B32: Commercial borrowings
B33: Deferred credit / hire purchase
B34: Borrowings from govt. of india
B35: Sales tax loan - govt.
B37: Secured short term loans - instn
B38: Secured short term loans - banks
B39: Secured short term loans - others
B40: Short term loan | C40: =SUM(C31:C39) -> 0 | D40: =SUM(D31:D39) -> 0 | E40: =SUM(E31:E39) -> 0 | F40: =SUM(F31:F39) -> 0 | G40: =SUM(G31:G39) -> 0 | H40: =SUM(H31:H39) -> 0 | I40: =SUM(I31:I39) -> 0
B42: Hire purchase / financial lease
B43: Vehicle loans
B44: Current maturity of debentures & bonds | C44: -4.532 | D44: -8.958
B45: Current maturity - others
B46: Other secured
B47: Amount payable within one year (secured)
B48: Secured loans | C48: =SUM(C17,C20,C24,C28,C40,C42:C46,C8:C13) -> 19.091 | D48: =SUM(D17,D20,D24,D28,D40,D42:D46,D8:D13) -> 54.811 | E48: =SUM(E17,E20,E24,E28,E40,E42:E46,E8:E13) -> 82.453738 | F48: =SUM(F17,F20,F24,F28,F40,F42:F46,F8:F13) -> 116.353 | G48: =SUM(G17,G20,G24,G28,G40,G42:G46,G8:G13) -> 171.758 | H48: =SUM(H17,H20,H24,H28,H40,H42:H46,H8:H13) -> 42.058 | I48: =SUM(I17,I20,I24,I28,I40,I42:I46,I8:I13) -> 417.48
B50: Fixed deposits - public
B51: Loans and advances from subsidiaries
B52: Inter corporate deposits (unsecured)
B53: Foreign currency convertible notes
B54: Long term loan in foreign currency
B55: Loans - body corporate
B56: Security deposits
B57: Loans - banks | D57: 8.76 | E57: 3.365394
B58: Loans - govt.
B59: Loans - others | C59: 24.055 | D59: 15.509 | E59: 24.573346
B60: Unsec. short term - banks
B61: Unsec. short term - others
B62: Unsec. short term - institutions
B63: Commercial paper
B64: Deferred tax loan
B65: Bills discounted
B66: Interest accrued and due
B67: Other loans & advances (unsecured)
B68: Trade deposits
B69: Other deposits
B70: Current maturity of debentures & bonds | D70: -4.994
B71: Current maturity - others
B72: Other unsecured loan
B73: Unsecured loans | C73: =SUM(C50:C72) -> 24.055 | D73: =SUM(D50:D72) -> 19.275 | E73: =SUM(E50:E72) -> 27.93874 | F73: =SUM(F50:F72) -> 0 | G73: =SUM(G50:G72) -> 0 | H73: =SUM(H50:H72) -> 0 | I73: =SUM(I50:I72) -> 0
B74: Amount payable within one year (unsecured)
B76: Long term borrowings | C76: =C48+C73 -> 43.146 | D76: =D48+D73 -> 74.086 | E76: =E48+E73 -> 110.39248 | F76: =F48+F73 -> 116.353 | G76: =G48+G73 -> 171.758 | H76: =H48+H73 -> 42.058 | I76: =I48+I73 -> 417.48
B78: Ruppes loan -sec bank | E78: 19.754403 | F78: 52.57 | G78: 92.231 | H78: 199.3 | I78: 184.468
B79: Foreign currency loans -sec bank
B80: From bank - sec | C80: =SUM(C78:C79) -> 0 | D80: =SUM(D78:D79) -> 0 | E80: =SUM(E78:E79) -> 19.754403 | F80: =SUM(F78:F79) -> 52.57 | G80: =SUM(G78:G79) -> 92.231 | H80: =SUM(H78:H79) -> 199.3 | I80: =SUM(I78:I79) -> 184.468
B82: Ruppes loan- sec inst
B83: Foreign currency loans- sec ins
B84: From institution- sec | C84: =SUM(C82:C83) -> 0 | D84: =SUM(D82:D83) -> 0 | E84: =SUM(E82:E83) -> 0 | F84: =SUM(F82:F83) -> 0 | G84: =SUM(G82:G83) -> 0 | H84: =SUM(H82:H83) -> 0 | I84: =SUM(I82:I83) -> 0
B86: Overdraft- sec ecl
B87: Cash credit & packing credit-sec wcl
B88: Others- sec wcl
B89: Working capital loans- sec | C89: =SUM(C86:C88) -> 0 | D89: =SUM(D86:D88) -> 0 | E89: =SUM(E86:E88) -> 0 | F89: =SUM(F86:F88) -> 0 | G89: =SUM(G86:G88) -> 0 | H89: =SUM(H86:H88) -> 0 | I89: =SUM(I86:I88) -> 0
B91: Buyers credits -sec
B92: Commercial borrowings- sec
B93: Other secured loans- sec
B94: Secured st loans repayable on demands | C94: =SUM(C80,C84,C89,C91:C93) -> 0 | D94: =SUM(D80,D84,D89,D91:D93) -> 0 | E94: =SUM(E80,E84,E89,E91:E93) -> 19.754403 | F94: =SUM(F80,F84,F89,F91:F93) -> 52.57 | G94: =SUM(G80,G84,G89,G91:G93) -> 92.231 | H94: =SUM(H80,H84,H89,H91:H93) -> 199.3 | I94: =SUM(I80,I84,I89,I91:I93) -> 184.468
B96: Ruppes loan - unsec bank | E96: 4.104165 | F96: 0.048
B97: Foreign currency loans - unsec bank
B98: From bank- unsec | C98: =SUM(C96:C97) -> 0 | D98: =SUM(D96:D97) -> 0 | E98: =SUM(E96:E97) -> 4.104165 | F98: =SUM(F96:F97) -> 0.048 | G98: =SUM(G96:G97) -> 0 | H98: =SUM(H96:H97) -> 0 | I98: =SUM(I96:I97) -> 0
B100: Ruppes loan - unsec inst
B101: Foreign currency loans - unsec inst
B102: From institution - unsec | C102: =SUM(C100:C101) -> 0 | D102: =SUM(D100:D101) -> 0 | E102: =SUM(E100:E101) -> 0 | F102: =SUM(F100:F101) -> 0 | G102: =SUM(G100:G101) -> 0 | H102: =SUM(H100:H101) -> 0 | I102: =SUM(I100:I101) -> 0
B104: Overdraft- unsec wcl
B105: Cash credit & packing credit- unsec wcl
B106: Others- unsec wcl
B107: Working capital loans - unsec | C107: =SUM(C104:C106) -> 0 | D107: =SUM(D104:D106) -> 0 | E107: =SUM(E104:E106) -> 0 | F107: =SUM(F104:F106) -> 0 | G107: =SUM(G104:G106) -> 0 | H107: =SUM(H104:H106) -> 0 | I107: =SUM(I104:I106) -> 0
B109: Buyers credits - unsec
B110: Commercial borrowings- unsec | I110: -63.765
B111: Commercial papers- unsec
B112: Security deposits / deposits
B113: Loans from related party | C113: 15.729 | D113: 19.171 | E113: 27.088002 | F113: 0.465 | I113: 63.765
B114: Other unsecured loans | C114: 5.8 | D114: 6.427
B115: Unsecured st loans repayable on demands | C115: =SUM(C98,C102,C107,C109:C114) -> 21.529 | D115: =SUM(D98,D102,D107,D109:D114) -> 25.598 | E115: =SUM(E98,E102,E107,E109:E114) -> 31.192167 | F115: =SUM(F98,F102,F107,F109:F114) -> 0.513 | G115: =SUM(G98,G102,G107,G109:G114) -> 0 | H115: =SUM(H98,H102,H107,H109:H114) -> 0 | I115: =SUM(I98,I102,I107,I109:I114) -> 0
B117: Short term borrowings | C117: =C94+C115 -> 21.529 | D117: =D94+D115 -> 25.598 | E117: =E94+E115 -> 50.94657 | F117: =F94+F115 -> 53.083 | G117: =G94+G115 -> 92.231 | H117: =H94+H115 -> 199.3 | I117: =I94+I115 -> 184.468
B119: Bank overdraft / short term credit
B120: Current maturity of debentures & bonds
...

Sheet Other liabilities
B1: =+Cover!B3 -> Knowledge Marine & Engineering Works Ltd.
B3: Other liabilities
B4: Rs mm | C4: Mar-18(A) | D4: Mar-19(A) | E4: Mar-20(A) | F4: Mar-21(A) | G4: Mar-22(A) | H4: Mar-23(A) | I4: Mar-24(A)
C5: Consolidated | D5: Consolidated | E5: Consolidated | F5: Consolidated | G5: Consolidated | H5: Consolidated | I5: Consolidated
B6: Sundry debtors
B7: Provisions for expenses
B8: Diminution in value of investment
B9: Doubtful advances
B10: Voluntary retirement scheme | C10: 0.009 | D10: 0.004
B11: Other current assets
B12: Current liabilities
B13: Carried forward loss
B14: Unabsorbed depreciation
B15: Accrued expenses deductible on payment
B16: Other deferred assets | D16: 1.089
B17: Deferred tax assets | C17: =SUM(C6:C16) -> 0.009 | D17: =SUM(D6:D16) -> 1.093 | E17: =SUM(E6:E16) -> 0 | F17: =SUM(F6:F16) -> 0 | G17: =SUM(G6:G16) -> 0 | H17: =SUM(H6:H16) -> 0 | I17: =SUM(I6:I16) -> 0
B19: Depreciation | C19: 3.693 | D19: 1.051
B20: Miscellaneous expenditure
B21: Fixed assets
B22: Pre-operative expenses incl. in cwip
B23: Prepaid lease rentals
B24: Other deferred liabilities | C24: 0.029 | D24: 3.713 | E24: 9.473117 | F24: 21.39 | G24: 30.528 | H24: 43.611 | I24: 55.338
B25: Deferred tax liability | C25: =SUM(C19:C24) -> 3.722 | D25: =SUM(D19:D24) -> 4.764 | E25: =SUM(E19:E24) -> 9.473117 | F25: =SUM(F19:F24) -> 21.39 | G25: =SUM(G19:G24) -> 30.528 | H25: =SUM(H19:H24) -> 43.611 | I25: =SUM(I19:I24) -> 55.338
B27: Deferred tax assets / liabilities | C27: =C25-C17 -> 3.713 | D27: =D25-D17 -> 3.671 | E27: =E25-E17 -> 9.473117 | F27: =F25-F17 -> 21.39 | G27: =G25-G17 -> 30.528 | H27: =H25-H17 -> 43.611 | I27: =I25-I17 -> 55.338
B29: Lease equalisation charges
B30: Sundry deposits- oltl
B31: Interest accrued but not due -oltl
B32: Govt grants
B33: Loans & advances to employees \directors
B34: Loans & advances to other
B35: Loans & advances to subsidiary
B36: Other lt trade deposits
B37: Other lt others | C37: 19.403 | D37: 18.969
B38: Other long term liabilities | C38: =SUM(C29:C37) -> 19.403 | D38: =SUM(D29:D37) -> 18.969 | E38: =SUM(E29:E37) -> 0 | F38: =SUM(F29:F37) -> 0 | G38: =SUM(G29:G37) -> 0 | H38: =SUM(H29:H37) -> 0 | I38: =SUM(I29:I37) -> 0
B40: Trade payables- lt
B41: Micro and small enterprises
B42: Lt payable others
B43: Long term trade payables | C43: =SUM(C40:C42) -> 0 | D43: =SUM(D40:D42) -> 0 | E43: =SUM(E40:E42) -> 0 | F43: =SUM(F40:F42) -> 0 | G43: =SUM(G40:G42) -> 0 | H43: =SUM(H40:H42) -> 0 | I43: =SUM(I40:I42) -> 0
B45: Lt provision for gratuity | C45: 0.026 | D45: 0.041 | F45: 0.473 | G45: 0.926 | H45: 1.616 | I45: 2.112
B46: Leave benefits
B47: Other employees benefits
B48: Contingency provisions
B49: Lt provision for tax
B50: Lt provision others
B51: Long term provisions | C51: =SUM(C45:C50) -> 0.026 | D51: =SUM(D45:D50) -> 0.041 | E51: =SUM(E45:E50) -> 0 | F51: =SUM(F45:F50) -> 0.473 | G51: =SUM(G45:G50) -> 0.926 | H51: =SUM(H45:H50) -> 1.616 | I51: =SUM(I45:I50) -> 2.112
B53: Other long term liabilities | C53: =C38+C43+C51 -> 19.429 | D53: =D38+D43+D51 -> 19.01 | E53: =E38+E43+E51 -> 0 | F53: =F38+F43+F51 -> 0.473 | G53: =G38+G43+G51 -> 0.926 | H53: =H38+H43+H51 -> 1.616 | I53: =I38+I43+I51 -> 2.112

Sheet Other assets
B1: =+Cover!B3 -> Knowledge Marine & Engineering Works Ltd.
B3: Other assets
B4: Rs mm | C4: Mar-18(A) | D4: Mar-19(A) | E4: Mar-20(A) | F4: Mar-21(A) | G4: Mar-22(A) | H4: Mar-23(A) | I4: Mar-24(A)
C5: Consolidated | D5: Consolidated | E5: Consolidated | F5: Consolidated | G5: Consolidated | H5: Consolidated | I5: Consolidated
B6: Government and other securities
B7: Mutual funds units
B8: Quoted equity shares
B9: Quoted preference shares
B10: Quoted debentures / bonds
B12: Equity
B13: Preference shares
B14: Debentures / bonds / fixed deposits
B15: Subsidiary companies | C15: =SUM(C12:C14) -> 0 | D15: =SUM(D12:D14) -> 0 | E15: =SUM(E12:E14) -> 0 | F15: =SUM(F12:F14) -> 0 | G15: =SUM(G12:G14) -> 0 | H15: =SUM(H12:H14) -> 0 | I15: =SUM(I12:I14) -> 0
B17: Joint venture & associated companies
B18: Other long term quoted investments
B19: Quoted | C19: =SUM(C6:C10,C17:C18,C15) -> 0 | D19: =SUM(D6:D10,D17:D18,D15) -> 0 | E19: =SUM(E6:E10,E17:E18,E15) -> 0 | F19: =SUM(F6:F10,F17:F18,F15) -> 0 | G19: =SUM(G6:G10,G17:G18,G15) -> 0 | H19: =SUM(H6:H10,H17:H18,H15) -> 0 | I19: =SUM(I6:I10,I17:I18,I15) -> 0
B21: Government and other securities
B22: Mutual funds units | D22: 0.11 | E22: 0.11
B23: Unquoted equity shares
B24: Unquoted preference shares
B25: Unquoted debentures / bonds
B27: Equity
B28: Preference shares
B29: Debentures / bonds / fixed deposits
B30: Subsidiary companies | C30: =SUM(C27:C29) -> 0 | D30: =SUM(D27:D29) -> 0 | E30: =SUM(E27:E29) -> 0 | F30: =SUM(F27:F29) -> 0 | G30: =SUM(G27:G29) -> 0 | H30: =SUM(H27:H29) -> 0 | I30: =SUM(I27:I29) -> 0
B32: Other long term unquoted investments | C32: 0.798 | D32: 10.95 | E32: 14.613733 | F32: 2.764 | G32: 29.577 | H32: 113.055 | I32: 294.001
B33: Unquoted | C33: =SUM(C21:C25,C32:C32,C30) -> 0.798 | D33: =SUM(D21:D25,D32:D32,D30) -> 11.06 | E33: =SUM(E21:E25,E32:E32,E30) -> 14.723733 | F33: =SUM(F21:F25,F32:F32,F30) -> 2.764 | G33: =SUM(G21:G25,G32:G32,G30) -> 29.577 | H33: =SUM(H21:H25,H32:H32,H30) -> 113.055 | I33: =SUM(I21:I25,I32:I32,I30) -> 294.001
B34: Less: prov for diminution in value of invest.
B35: Long term investment | C35: =C19+C33+C34 -> 0.798 | D35: =D19+D33+D34 -> 11.06 | E35: =E19+E33+E34 -> 14.723733 | F35: =F19+F33+F34 -> 2.764 | G35: =G19+G33+G34 -> 29.577 | H35: =H19+H33+H34 -> 113.055 | I35: =I19+I33+I34 -> 294.001
B36: Non current investments | C36: =C35 -> 0.798 | D36: =D35 -> 11.06 | E36: =E35 -> 14.723733 | F36: =F35 -> 2.764 | G36: =G35 -> 29.577 | H36: =H35 -> 113.055 | I36: =I35 -> 294.001
B38: Considered good
B39: Considered doubtfull
B40: Less: provision for doubtful receivable
B41: Long term trade receivable | C41: =SUM(C38:C40) -> 0 | D41: =SUM(D38:D40) -> 0 | E41: =SUM(E38:E40) -> 0 | F41: =SUM(F38:F40) -> 0 | G41: =SUM(G38:G40) -> 0 | H41: =SUM(H38:H40) -> 0 | I41: =SUM(I38:I40) -> 0
B42: Balances with custom & excise | C42: 0.419 | D42: 0.967
B43: Lt loans & adv. others | G43: 20.05 | H43: 8.878
B44: Advances to vendors
B45: Other loans and advances : | C45: =SUM(C43:C44) -> 0 | D45: =SUM(D43:D44) -> 0 | E45: =SUM(E43:E44) -> 0 | F45: =SUM(F43:F44) -> 0 | G45: =SUM(G43:G44) -> 20.05 | H45: =SUM(H43:H44) -> 8.878 | I45: =SUM(I43:I44) -> 0
B46: Less : provision for doubtful advances - long term loans & advances
B47: Long term loans & advances | C47: =SUM(C41,C42:C42,C46,C45) -> 0.419 | D47: =SUM(D41,D42:D42,D46,D45) -> 0.967 | E47: =SUM(E41,E42:E42,E46,E45) -> 0 | F47: =SUM(F41,F42:F42,F46,F45) -> 0 | G47: =SUM(G41,G42:G42,G46,G45) -> 20.05 | H47: =SUM(H41,H42:H42,H46,H45) -> 8.878 | I47: =SUM(I41,I42:I42,I46,I45) -> 0
B49: Claims and other receivables
B50: Fixed deposits with banks with maturity period more than months
B51: Interest accrued
B52: Pre paid expenses
B53: Future & options contract
B54: Non current inventories
B55: Non current portion of cash & bank balances
B56: Other non current assets- other
B57: Other non current assets | C57: =SUM(C49:C56) -> 0 | D57: =SUM(D49:D56) -> 0 | E57: =SUM(E49:E56) -> 0 | F57: =SUM(F49:F56) -> 0 | G57: =SUM(G49:G56) -> 0 | H57: =SUM(H49:H56) -> 0 | I57: =SUM(I49:I56) -> 0
B59: Cash in hand | C59: 1.17 | D59: 1.086 | E59: 0.610032 | F59: 1.805 | G59: 0.184 | H59: 0.555 | I59: 2.195
B60: In currents a/c (by defaults) | C60: 0.583 | D60: 73.117 | E60: 15.603129 | F60: 46.278 | G60: 165.754 | H60: 10.013 | I60: 137.453
B61: In fixed deposits a/c | F61: 67.229 | G61: 59.753 | H61: 549.336 | I61: 366.344
B62: With scheduled banks | C62: =SUM(C60:C61) -> 0.583 | D62: =SUM(D60:D61) -> 73.117 | E62: =SUM(E60:E61) -> 15.603129 | F62: =SUM(F60:F61) -> 113.507 | G62: =SUM(G60:G61) -> 225.507 | H62: =SUM(H60:H61) -> 559.349 | I62: =SUM(I60:I61) -> 503.797
B63: With other bank
B64: Balances at bank | C64: =C62+C63 -> 0.583 | D64: =D62+D63 -> 73.117 | E64: =E62+E63 -> 15.603129 | F64: =F62+F63 -> 113.507 | G64: =G62+G63 -> 225.507 | H64: =H62+H63 -> 559.349 | I64: =I62+I63 -> 503.797
B66: Account with post office
B67: Remittances in transit
B68: Stamps, cheques, demand drafts in hand
B69: Cash and bank | C69: =SUM(C59,C66:C68,C64) -> 1.753 | D69: =SUM(D59,D66:D68,D64) -> 74.203 | E69: =SUM(E59,E66:E68,E64) -> 16.213161 | F69: =SUM(F59,F66:F68,F64) -> 115.312 | G69: =SUM(G59,G66:G68,G64) -> 225.691 | H69: =SUM(H59,H66:H68,H64) -> 559.904 | I69: =SUM(I59,I66:I68,I64) -> 505.992
B71: Preliminary expenses
B72: Research and development expenditure
B73: Expenses on issue of shares / debentures
B74: Discounts on issue of shares / debentures
B75: Deferred revenue expenditure
B76: Pre-operative expenses
B77: Compensation on voluntary retirement
B78: Interest paid out of capital contruction
B79: Cost of trial run production
B80: Other miscellaneous expenses
B81: Miscellaneous expenses not written off | C81: =SUM(C71:C80) -> 0 | D81: =SUM(D71:D80) -> 0 | E81: =SUM(E71:E80) -> 0 | F81: =SUM(F71:F80) -> 0 | G81: =SUM(G71:G80) -> 0 | H81: =SUM(H71:H80) -> 0 | I81: =SUM(I71:I80) -> 0

Sheet PPE
B1: =+Cover!B3 -> Knowledge Marine & Engineering Works Ltd.
B3: PPE
B4: Rs mm | C4: Mar-18(A) | D4: Mar-19(A) | E4: Mar-20(A) | F4: Mar-21(A) | G4: Mar-22(A) | H4: Mar-23(A) | I4: Mar-24(A)
C5: Consolidated | D5: Consolidated | E5: Consolidated | F5: Consolidated | G5: Consolidated | H5: Consolidated | I5: Consolidated
B6: Goodwill | C6: 0.009 | D6: 0.009 | E6: 0.09 | F6: 0.009 | G6: 0.009 | H6: 0.009 | I6: 0.009
B7: Plant& machinery | C7: 6.26 | D7: 4.85 | E7: 295.082 | F7: 0.434 | G7: 0.641 | H7: 0.839 | I7: 0.839
B8: Furniture & fixtures & office appliances | C8: 0.942 | D8: 0.963 | E8: 0.972 | F8: 2.133 | G8: 3.027 | H8: 6.444 | I8: 6.64
B9: Vehicles | G9: 2.137 | H9: 2.137 | I9: 2.137
B10: Ships & vessels | C10: 109.138 | D10: 129.527 | F10: 317.862 | G10: 587.17 | H10: 687.977 | I10: 1225.524
B11: Computer software | F11: 0.036 | G11: 0.036 | H11: 0.036 | I11: 0.056
B12: Factory equipments | D12: 0.28
B13: Computer hardware | C13: 0.331 | D13: 0.582 | E13: 1.226 | F13: 1.842 | G13: 2.297 | H13: 4.008 | I13: 5.536
B14: Other fixed assets
B15: Other fixed assets revised | E15: -0.078691 | F15: 0.292 | G15: -0.008
B16: Gross block | C16: =SUM(C6:C15) -> 116.68 | D16: =SUM(D6:D15) -> 136.211 | E16: =SUM(E6:E15) -> 297.29131 | F16: =SUM(F6:F15) -> 322.608 | G16: =SUM(G6:G15) -> 595.309 | H16: =SUM(H6:H15) -> 701.45 | I16: =SUM(I6:I15) -> 1240.741
B18: Goodwill
B19: Plant & machinery | C19: -1.46 | D19: -4.568 | E19: -23.753 | F19: -0.111 | G19: -0.087 | H19: -0.222 | I19: -0.339
B20: Furniture & fixtures & office appliances | C20: -0.098 | D20: -0.215 | E20: -0.334 | F20: -0.194 | G20: -0.858 | H20: -1.227 | I20: -1.905
B21: Vehicles | G21: -0.117 | H21: -0.371 | I21: -0.625
B22: Ships & vessels | C22: -1.467 | D22: -8.931 | F22: -43.834 | G22: -67.176 | H22: -109.235 | I22: -167.933
B23: Computer software | F23: -0.002 | H23: -0.016 | I23: -0.023
B24: Factory equipments | D24: -0.28
B25: Computer hardware | C25: -0.088 | D25: -0.258 | E25: -0.484 | F25: -0.857 | G25: -1.312 | H25: -2.074 | I25: -3.073
B26: Other fixed assets
B27: Other fixed assets revised
B28: Less: accumulated depreciation | C28: =SUM(C18:C27) -> -3.113 | D28: =SUM(D18:D27) -> -14.252 | E28: =SUM(E18:E27) -> -24.571 | F28: =SUM(F18:F27) -> -44.998 | G28: =SUM(G18:G27) -> -69.55 | H28: =SUM(H18:H27) -> -113.145 | I28: =SUM(I18:I27) -> -173.898
B30: Less: impairment of assets
B32: Goodwill | C32: 0.009 | D32: 0.009 | E32: 0.09 | F32: 0.009 | G32: 0.009 | H32: 0.009 | I32: 0.009
B33: Plant & machinery | C33: 4.8 | D33: 0.282 | E33: 271.329 | F33: 0.323 | G33: 0.554 | H33: 0.617 | I33: 0.5
B34: Furniture & fixtures & office appliances | C34: 0.844 | D34: 0.748 | E34: 0.638 | F34: 1.939 | G34: 2.169 | H34: 5.217 | I34: 4.735
B35: Vehicles | E35: 0 | F35: 0 | G35: 2.02 | H35: 1.766 | I35: 1.512
B36: Ships & vessels | C36: 107.671 | D36: 120.596 | E36: 0 | F36: 274.028 | G36: 519.994 | H36: 578.742 | I36: 1057.591
B37: Computer software | E37: 0 | F37: 0.034 | G37: 0.036 | H37: 0.02 | I37: 0.033
B38: Factory equipments | D38: 0 | E38: 0 | F38: 0 | G38: 0 | H38: 0
B39: Computer hardware | C39: 0.243 | D39: 0.324 | E39: 0.742 | F39: 0.985 | G39: 0.985 | H39: 1.934 | I39: 2.463
B40: Other fixed assets | E40: 0 | F40: 0 | G40: 0 | H40: 0
B41: Other fixed assets revised | E41: -0.078691 | F41: 0.292 | G41: -0.008 | H41: 0
B42: Net block | C42: =SUM(C32:C41) -> 113.567 | D42: =SUM(D32:D41) -> 121.959 | E42: =SUM(E32:E41) -> 272.72031 | F42: =SUM(F32:F41) -> 277.61 | G42: =SUM(G32:G41) -> 525.759 | H42: =SUM(H32:H41) -> 588.305 | I42: =SUM(I32:I41) -> 1066.843
B44: Lease adjustment a/c
B45: Capital work in progress | D45: 75.286 | F45: 28.536 | G45: 18.08 | H45: 80.985 | I45: 120.383
B46: Intangible assets under development
B47: Pre-operative expenses pending
B48: Assets in transit

Sheet Working capital
B1: =+Cover!B3 -> Knowledge Marine & Engineering Works Ltd.
B3: Working capital
B4: Rs mm | C4: Mar-18(A) | D4: Mar-19(A) | E4: Mar-20(A) | F4: Mar-21(A) | G4: Mar-22(A) | H4: Mar-23(A) | I4: Mar-24(A)
C5: Consolidated | D5: Consolidated | E5: Consolidated | F5: Consolidated | G5: Consolidated | H5: Consolidated | I5: Consolidated
B7: Current liabilities
B8: For expenses
B9: For purchases | C9: 8.203 | D9: 71.466 | E9: 25.932757 | F9: 4.978 | G9: 61.682 | H9: 261.048 | I9: 121.705
B10: For capital goods
B11: Sundry creditors | C11: =SUM(C8:C10) -> 8.203 | D11: =SUM(D8:D10) -> 71.466 | E11: =SUM(E8:E10) -> 25.932757 | F11: =SUM(F8:F10) -> 4.978 | G11: =SUM(G8:G10) -> 61.682 | H11: =SUM(H8:H10) -> 261.048 | I11: =SUM(I8:I10) -> 121.705
B13: Acceptances
B14: Due to subsidiaries- trade payables
B15: Trade payables | C15: =SUM(C11,C13:C14) -> 8.203 | D15: =SUM(D11,D13:D14) -> 71.466 | E15: =SUM(E11,E13:E14) -> 25.932757 | F15: =SUM(F11,F13:F14) -> 4.978 | G15: =SUM(G11,G13:G14) -> 61.682 | H15: =SUM(H11,H13:H14) -> 261.048 | I15: =SUM(I11,I13:I14) -> 121.705
B17: Other liabilities | E17: 7.559003 | H17: 10.478 | I17: 10.478
B18: Other deposits
B19: Statutory liability | E19: 13.562719 | F19: 2.448 | G19: 13.904 | H19: 10.646 | I19: 2.595
B20: Other current liabilities | C20: =SUM(C17:C19) -> 0 | D20: =SUM(D17:D19) -> 0 | E20: =SUM(E17:E19) -> 21.121722 | F20: =SUM(F17:F19) -> 2.448 | G20: =SUM(G17:G19) -> 13.904 | H20: =SUM(H17:H19) -> 21.124 | I20: =SUM(I17:I19) -> 13.073
B22: Provision for tax | C22: 7.388 | D22: 8.923 | E22: 9.671756 | F22: 18.059 | G22: 62.371 | H22: 148.708 | I22: 88.119
B23: provision for gratuity
B24: Other provisions | C24: 3.918 | D24: 1.676 | E24: 3.867315 | F24: 4.363 | G24: 5.507 | H24: 5.164 | I24: 6.197
B25: Short term provisions | C25: =SUM(C22:C24) -> 11.306 | D25: =SUM(D22:D24) -> 10.599 | E25: =SUM(E22:E24) -> 13.539071 | F25: =SUM(F22:F24) -> 22.422 | G25: =SUM(G22:G24) -> 67.878 | H25: =SUM(H22:H24) -> 153.872 | I25: =SUM(I22:I24) -> 94.316
B27: Current assets loans & advances
B28: Currents investments | C28: =SUM(C36,C41,C40) -> 0 | D28: =SUM(D36,D41,D40) -> 0 | E28: =SUM(E36,E41,E40) -> 0 | F28: =SUM(F36,F41,F40) -> 0.587 | G28: =SUM(G36,G41,G40) -> 0 | H28: =SUM(H36,H41,H40) -> 0 | I28: =SUM(I36,I41,I40) -> 0
B29: Government and other securities
B30: Treasury bills
B31: Mutual funds units
B32: Quoted equity shares
B33: Quoted preference shares
B34: Quoted debentures / bonds
B35: Other current quoted investments
B36: Quoted | C36: =SUM(C29:C35) -> 0 | D36: =SUM(D29:D35) -> 0 | E36: =SUM(E29:E35) -> 0 | F36: =SUM(F29:F35) -> 0 | G36: =SUM(G29:G35) -> 0 | H36: =SUM(H29:H35) -> 0 | I36: =SUM(I29:I35) -> 0
B38: Mutual funds units | F38: 0.105
B39: Other current unquoted investments | F39: 0.482
B40: Current inv_ provision in dimunition in value of investment
B41: Unquoted | C41: =SUM(C38:C39) -> 0 | D41: =SUM(D38:D39) -> 0 | E41: =SUM(E38:E39) -> 0 | F41: =SUM(F38:F39) -> 0.587 | G41: =SUM(G38:G39) -> 0 | H41: =SUM(H38:H39) -> 0 | I41: =SUM(I38:I39) -> 0
B43: Current inv_ unquoted investments - book value | F43: 0.587
B45: Raw materials
B46: Work-in progress
B47: Finished goods
B48: Packing materials
B49: Shares, units, bonds in hand
B50: Stores and spare
B51: Consumable tools | E51: 2.695134 | F51: 3.197 | G51: 1.888
B52: Goods in transit
B53: Goods in trade | H53: 11.425 | I53: 12.165
B54: Less: advance received wip
B55: Excise duty on finished goods
B56: Other inventory | F56: 0.101
B57: Inventories | C57: =SUM(C45:C56) -> 0 | D57: =SUM(D45:D56) -> 0 | E57: =SUM(E45:E56) -> 2.695134 | F57: =SUM(F45:F56) -> 3.298 | G57: =SUM(G45:G56) -> 1.888 | H57: =SUM(H45:H56) -> 11.425 | I57: =SUM(I45:I56) -> 12.165
B59: Considered good | C59: 0.122 | D59: 0.122 | H59: 99.8 | I59: 198.585
B60: Considered doubtful
B61: Debtors more than six months | C61: =SUM(C59:C60) -> 0.122 | D61: =SUM(D59:D60) -> 0.122 | E61: =SUM(E59:E60) -> 0 | F61: =SUM(F59:F60) -> 0 | G61: =SUM(G59:G60) -> 0 | H61: =SUM(H59:H60) -> 99.8 | I61: =SUM(I59:I60) -> 198.585
B63: Considered good | C63: 16.384 | D63: 10.181 | E63: 30.294803 | F63: 3.969 | G63: 39.428 | H63: 458.205 | I63: 233.468
B64: Considered doubtful
B65: Debtors others | C65: =SUM(C63:C64) -> 16.384 | D65: =SUM(D63:D64) -> 10.181 | E65: =SUM(E63:E64) -> 30.294803 | F65: =SUM(F63:F64) -> 3.969 | G65: =SUM(G63:G64) -> 39.428 | H65: =SUM(H63:H64) -> 458.205 | I65: =SUM(I63:I64) -> 233.468
B66: Less: provisions for doubtful debts
B67: Considered good
B68: Considered doubtful
B69: Hire purchase receivables | C69: =SUM(C67:C68) -> 0 | D69: =SUM(D67:D68) -> 0 | E69: =SUM(E67:E68) -> 0 | F69: =SUM(F67:F68) -> 0 | G69: =SUM(G67:G68) -> 0 | H69: =SUM(H67:H68) -> 0 | I69: =SUM(I67:I68) -> 0
B70: Less: provisions for doubtful receivables
B71: Sundry debtors | C71: =SUM(C61,C65,C66,C69,C70) -> 16.506 | D71: =SUM(D61,D65,D66,D69,D70) -> 10.303 | E71: =SUM(E61,E65,E66,E69,E70) -> 30.294803 | F71: =SUM(F61,F65,F66,F69,F70) -> 3.969 | G71: =SUM(G61,G65,G66,G69,G70) -> 39.428 | H71: =SUM(H61,H65,H66,H69,H70) -> 558.005 | I71: =SUM(I61,I65,I66,I69,I70) -> 432.053
B74: Prepaid expenses | G74: 0.02 | H74: 0.468 | I74: 0.648
B75: Claims received
B76: Other_current_assets | C76: 0 | D76: 0.408 | E76: 0.029628 | F76: 7.516 | G76: 0 | H76: 0 | I76: 34.261
B77: Accrued gain on forward contracts (net)
B78: Other current assets | C78: =SUM(C74:C77) -> 0 | D78: =SUM(D74:D77) -> 0.408 | E78: =SUM(E74:E77) -> 0.029628 | F78: =SUM(F74:F77) -> 7.516 | G78: =SUM(G74:G77) -> 0.02 | H78: =SUM(H74:H77) -> 0.468 | I78: =SUM(I74:I77) -> 34.909
B80: For purchases | D80: 0.559 | G80: 2.296 | H80: 0.409 | I80: 47.343
B81: For capital expenditures
B82: To others | E82: 0.32073 | F82: 42.89 | G82: 11.659 | H82: 11.574 | I82: -63.765
B83: Advances recoverable in cash or in kind | C83: =SUM(C80:C82) -> 0 | D83: =SUM(D80:D82) -> 0.559 | E83: =SUM(E80:E82) -> 0.32073 | F83: =SUM(F80:F82) -> 42.89 | G83: =SUM(G80:G82) -> 13.955 | H83: =SUM(H80:H82) -> 11.983 | I83: =SUM(I80:I82) -> -16.422
B84: Advance income tax and tds | C84: 7.596 | D84: 3.671
B85: To employees | D85: 0.01
B86: To others | C86: 0 | D86: 0.02 | E86: 0 | F86: 0 | G86: 0 | H86: 0 | I86: 29.504
B87: Loans | C87: =SUM(C85:C86) -> 0 | D87: =SUM(D85:D86) -> 0.03 | E87: =SUM(E85:E86) -> 0 | F87: =SUM(F85:F86) -> 0 | G87: =SUM(G85:G86) -> 0 | H87: =SUM(H85:H86) -> 0 | I87: =SUM(I85:I86) -> 29.504
B89: Balances with customs and excise authorities | E89: 8.333454 | F89: 23.994 | G89: 57.653 | H89: 152.808 | I89: 101.488
B90: Sundry deposits | E90: 3.829844 | F90: 2.444 | G90: 4.695 | H90: 3.022 | I90: 3.748
B91: Mat credit entitlement | C91: 0.287 | D91: 0.999 | E91: 5.70312
B92: Other loans & advances | C92: 0.003 | E92: 0.200151 | F92: 1.438 | I92: 0.397
B94: Less: advances considered doubtful
B95: Short term loans and advances | C95: =SUM(C83,C84:C84,C89:C92,C94,C87) -> 7.886 | D95: =SUM(D83,D84:D84,D89:D92,D94,D87) -> 5.259 | E95: =SUM(E83,E84:E84,E89:E92,E94,E87) -> 18.387299 | F95: =SUM(F83,F84:F84,F89:F92,F94,F87) -> 70.766 | G95: =SUM(G83,G84:G84,G89:G92,G94,G87) -> 76.303 | H95: =SUM(H83,H84:H84,H89:H92,H94,H87) -> 167.813 | I95: =SUM(I83,I84:I84,I89:I92,I94,I87) -> 118.715
B96: Amt due from firm (directors interested)
B98: Liabilities under guarantees | C98: 30.826 | D98: 36.887 | E98: 13.886 | F98: 18.625 | G98: 56.012 | H98: 105.589 | I98: 356.214
B99: Contingent liabilities | C99: =SUM(C98:C98) -> 30.826 | D99: =SUM(D98:D98) -> 36.887 | E99: =SUM(E98:E98) -> 13.886 | F99: =SUM(F98:F98) -> 18.625 | G99: =SUM(G98:G98) -> 56.012 | H99: =SUM(H98:H98) -> 105.589 | I99: =SUM(I98:I98) -> 356.214

Sheet Revenue & OI
B1: =+Cover!B3 -> Knowledge Marine & Engineering Works Ltd.
B3: Revenue and other income
B4: Rs mm | C4: Mar-18(A) | D4: Mar-19(A) | E4: Mar-20(A) | F4: Mar-21(A) | G4: Mar-22(A) | H4: Mar-23(A) | I4: Mar-24(A)
C5: Consolidated | D5: Consolidated | E5: Consolidated | F5: Consolidated | G5: Consolidated | H5: Consolidated | I5: Consolidated
B6: Charter income | C6: 106.009 | D6: 105.672 | E6: 239.08809 | F6: 332.822 | G6: 611.063 | H6: 2015.296 | I6: 1635.831
B7: Sales turnover | C7: =SUM(C6:C6) -> 106.009 | D7: =SUM(D6:D6) -> 105.672 | E7: =SUM(E6:E6) -> 239.08809 | F7: =SUM(F6:F6) -> 332.822 | G7: =SUM(G6:G6) -> 611.063 | H7: =SUM(H6:H6) -> 2015.296 | I7: =SUM(I6:I6) -> 1635.831
B8: Less: inter divisional transfers
B9: Less: sales returns
B10: Less: excise
B11: Net sales | C11: =SUM(C7,C8:C10) -> 106.009 | D11: =SUM(D7,D8:D10) -> 105.672 | E11: =SUM(E7,E8:E10) -> 239.08809 | F11: =SUM(F7,F8:F10) -> 332.822 | G11: =SUM(G7,G8:G10) -> 611.063 | H11: =SUM(H7,H8:H10) -> 2015.296 | I11: =SUM(I7,I8:I10) -> 1635.831
B14: Foreign exchange gains | E14: 0.158154
B15: Provision written back | E15: 1.639629 | F15: 0.136 | G15: 0.518 | H15: 0.017
B16: Discounts | E16: 0.014312 | H16: 0.001 | I16: 0.01
B17: Sale of scrap - other income | G17: 0.945
B18: Interest on others | C18: 0.41 | D18: 0.28 | E18: 0.895735 | F18: 1.2 | G18: 3.645 | H18: 13.805 | I18: 31.221
B19: Interest received | C19: =SUM(C18:C18) -> 0.41 | D19: =SUM(D18:D18) -> 0.28 | E19: =SUM(E18:E18) -> 0.895735 | F19: =SUM(F18:F18) -> 1.2 | G19: =SUM(G18:G18) -> 3.645 | H19: =SUM(H18:H18) -> 13.805 | I19: =SUM(I18:I18) -> 31.221
B20: Gain on forward contracts/forex
B21: Others | I21: 0.026
B22: Other income | C22: =SUM(C19,C20:C21,C14:C16) -> 0.41 | D22: =SUM(D19,D20:D21,D14:D16) -> 0.28 | E22: =SUM(E19,E20:E21,E14:E16) -> 2.70783 | F22: =SUM(F19,F20:F21,F14:F16) -> 1.336 | G22: =SUM(G19,G20:G21,G14:G16) -> 4.163 | H22: =SUM(H19,H20:H21,H14:H16) -> 13.823 | I22: =SUM(I19,I20:I21,I14:I16) -> 31.257

Sheet Expenses
B1: =+Cover!B3 -> Knowledge Marine & Engineering Works Ltd.
B3: Expenses
B4: Rs mm | C4: Mar-18(A) | D4: Mar-19(A) | E4: Mar-20(A) | F4: Mar-21(A) | G4: Mar-22(A) | H4: Mar-23(A) | I4: Mar-24(A)
C5: Consolidated | D5: Consolidated | E5: Consolidated | F5: Consolidated | G5: Consolidated | H5: Consolidated | I5: Consolidated
B7: Opening - work in progress
B8: Opening - finished goods
B9: Opening - shares, units and bonds
B10: Opening - food & beverages
B11: Other opening balances
B12: Less: closing - work in progress
B13: Less: closing - finished goods
B14: Less: closing - shares, units and bonds
B15: Closing - food & beverages
B16: Less: other closing balances
B17: Inter division transfer in transits
B18: Excise duty on stock adjustments | C18: 0 | D18: 0 | E18: 0 | F18: 0 | G18: 0 | H18: 0 | I18: 0
B19: Stock capitalised
B20: Increase/decrease in stock | C20: =SUM(C7:C19) -> 0 | D20: =SUM(D7:D19) -> 0 | E20: =SUM(E7:E19) -> 0 | F20: =SUM(F7:F19) -> 0 | G20: =SUM(G7:G19) -> 0 | H20: =SUM(H7:H19) -> 0 | I20: =SUM(I7:I19) -> 0
B22: Opening raw materials
B23: Purchases raw materials
B24: Development rights
B25: Closing raw materials
B26: Other direct purchases / brought in cost
B27: Stock on amalgamation
B28: Others | E28: 11.185403 | F28: 12.512 | G28: 6.95 | H28: 52.126 | I28: 67.871
B29: Raw material consumed capitalised
B30: Raw material consumed | C30: =SUM(C22:C29) -> 0 | D30: =SUM(D22:D29) -> 0 | E30: =SUM(E22:E29) -> 11.185403 | F30: =SUM(F22:F29) -> 12.512 | G30: =SUM(G22:G29) -> 6.95 | H30: =SUM(H22:H29) -> 52.126 | I30: =SUM(I22:I29) -> 67.871
B32: Electricity & power | C32: 0.11 | D32: 0.036 | E32: 0.046234 | F32: 0.192 | G32: 0.22 | H32: 0.239 | I32: 0.738
B33: Less: captive consumption of power
B34: Oil, fuel & natural gas | C34: 1.947 | D34: 14.994 | E34: 53.594814 | F34: 49.571 | G34: 73.832 | H34: 169.343 | I34: 92.597
B35: Less: captive consumption of fuel
B36: Power & fuel cost | C36: =SUM(C32:C35) -> 2.057 | D36: =SUM(D32:D35) -> 15.03 | E36: =SUM(E32:E35) -> 53.641048 | F36: =SUM(F32:F35) -> 49.763 | G36: =SUM(G32:G35) -> 74.052 | H36: =SUM(H32:H35) -> 169.582 | I36: =SUM(I32:I35) -> 93.335
B38: Sub-contracted / outsourced services | C38: 49.427 | E38: 53.510632 | F38: 67.468 | G38: 112.796 | H38: 933.427 | I38: 785.829
B39: Port, light and canal dues | C39: 0.294 | D39: 1.203
B40: Other repairs | C40: 0.231 | E40: 14.806597 | F40: 17.928 | G40: 6.215 | H40: 44.503 | I40: 14.248
B41: Repairs and maintenance | C41: =SUM(C40:C40) -> 0.231 | D41: =SUM(D40:D40) -> 0 | E41: =SUM(E40:E40) -> 14.806597 | F41: =SUM(F40:F40) -> 17.928 | G41: =SUM(G40:G40) -> 6.215 | H41: =SUM(H40:H40) -> 44.503 | I41: =SUM(I40:I40) -> 14.248
B43: Dry docking charges | I43: 2.66
B44: Agency fees | F44: 0.755 | G44: 1.841 | H44: 9.603 | I44: 13.057
B45: Ship management fees paid | F45: 2.725 | G45: 3.695 | H45: 15.849 | I45: 13.32
B46: Stores, spare parts and tools consumed | C46: 0.298 | D46: 4.895
B47: Crew expenses | E47: 27.450422 | F47: 31.272 | G47: 41.506 | H47: 61.619 | I47: 82.048
B48: Charter hire expenses | C48: 0.174 | E48: 90.739544 | F48: 165.616 | G48: 182.353 | H48: 129.835 | I48: 31.49
B49: Other operating and mfg expenses | C49: 8.239 | D49: 8.546 | E49: 13.259734 | F49: 50.831 | G49: 49.347 | H49: 33.673 | I49: 51.147
B50: Manufacturing expenses capitalised | E50: -142.38648 | F50: -238.07 | G50: -248.292 | H50: -210.157 | I50: -166.886
B51: Operating & manufacturing expenses | C51: =SUM(C38:C39,C43:C50,C41) -> 58.663 | D51: =SUM(D38:D39,D43:D50,D41) -> 14.644 | E51: =SUM(E38:E39,E43:E50,E41) -> 57.380445 | F51: =SUM(F38:F39,F43:F50,F41) -> 98.525 | G51: =SUM(G38:G39,G43:G50,G41) -> 149.461 | H51: =SUM(H38:H39,H43:H50,H41) -> 1018.352 | I51: =SUM(I38:I39,I43:I50,I41) -> 826.913
B53: Cost of goods sold | C53: =C20+C30+C36+C51+C74 -> 60.72 | D53: =D20+D30+D36+D51+D74 -> 29.674 | E53: =E20+E30+E36+E51+E74 -> 122.2069 | F53: =F20+F30+F36+F51+F74 -> 160.8 | G53: =G20+G30+G36+G51+G74 -> 230.463 | H53: =H20+H30+H36+H51+H74 -> 1240.06 | I53: =I20+I30+I36+I51+I74 -> 988.119
B55: Salaries, wages & bonus | C55: 4.191 | D55: 8.463 | E55: 8.057489 | F55: 9.784 | G55: 15.566 | H55: 21.402 | I55: 27.337
B56: Workmen and staff welfare expenses | C56: 0.1 | D56: 0.976 | E56: 0.995057 | F56: 0.82 | G56: 1.516 | H56: 5.151 | I56: 5.18
B57: Gratuity & ex gratia | F57: 0.494 | G57: 0.496 | H57: 0.626 | I57: 0.495
B58: Other employees cost | C58: 0.067 | D58: 0.024 | E58: 0.096893 | F58: 1.004 | G58: 1.19 | H58: 2.297 | I58: 4.596
B59: Employee cost | C59: =SUM(C55:C58) -> 4.358 | D59: =SUM(D55:D58) -> 9.463 | E59: =SUM(E55:E58) -> 9.149439 | F59: =SUM(F55:F58) -> 12.102 | G59: =SUM(G55:G58) -> 18.768 | H59: =SUM(H55:H58) -> 29.476 | I59: =SUM(I55:I58) -> 37.608
B61: For own use
B62: For service delivery to clients
B63: Software purchase | C63: =SUM(C61:C62) -> 0 | D63: =SUM(D61:D62) -> 0 | E63: =SUM(E61:E62) -> 0 | F63: =SUM(F61:F62) -> 0 | G63: =SUM(G61:G62) -> 0 | H63: =SUM(H61:H62) -> 0 | I63: =SUM(I61:I62) -> 0
B65: For subsidiaries
B66: For others
B67: Technical sub-contractors | C67: =SUM(C65:C66) -> 0 | D67: =SUM(D65:D66) -> 0 | E67: =SUM(E65:E66) -> 0 | F67: =SUM(F65:F66) -> 0 | G67: =SUM(G65:G66) -> 0 | H67: =SUM(H65:H66) -> 0 | I67: =SUM(I65:I66) -> 0
B69: Software developments expenses
B70: Software license cost
B71: Other software development expenses
B72: Other operating expenses
B73: Cost of software developments capitalised
B74: Cost of software development | C74: =SUM(C63,C67,C69:C73) -> 0 | D74: =SUM(D63,D67,D69:D73) -> 0 | E74: =SUM(E63,E67,E69:E73) -> 0 | F74: =SUM(F63,F67,F69:F73) -> 0 | G74: =SUM(G63,G67,G69:G73) -> 0 | H74: =SUM(H63,H67,H69:H73) -> 0 | I74: =SUM(I63,I67,I69:I73) -> 0
B76: Rent | C76: 0.484 | D76: 0.874 | E76: 1.0514 | F76: 1.726 | G76: 2.017 | H76: 2.209 | I76: 4.501
B77: Rates & taxes | C77: 0.218 | D77: 0.203 | E77: 0.066173 | F77: 0.443 | G77: 1.082 | H77: 2.939 | I77: 5.525
B78: Others | D78: 0.045
B79: Rent, taxes and lighting | C79: =SUM(C76:C78) -> 0.702 | D79: =SUM(D76:D78) -> 1.122 | E79: =SUM(E76:E78) -> 1.117573 | F79: =SUM(F76:F78) -> 2.169 | G79: =SUM(G76:G78) -> 3.099 | H79: =SUM(H76:H78) -> 5.148 | I79: =SUM(I76:I78) -> 10.026
B81: Repairs & maintenance - others | C81: 0.207 | D81: 0.593 | I81: 2.593
B82: Printing and stationery | C82: 0.086 | D82: 0.143 | E82: 0.253283 | F82: 0.157 | G82: 0.352 | H82: 0.571 | I82: 0.971
B83: Professional and legal fees | C83: 3.709 | D83: 6.763 | E83: 8.988955 | F83: 10.566 | G83: 7.961 | H83: 17.502 | I83: 43.522
B84: Audit work | C84: 0.36 | D84: 0.557 | E84: 0.631 | F84: 0.457 | G84: 0.405 | H84: 0.535 | I84: 0.515
B85: Taxation work | F85: 0.17 | G85: 0.199 | H85: 0.203 | I85: 0.203
B86: Certification work
B87: Reimbursement of expenses
B88: Other audit exp | F88: 0.115 | G88: 0.185 | H88: 0.168 | I88: 0.533
B89: Others | C89: =SUM(C84:C88) -> 0.36 | D89: =SUM(D84:D88) -> 0.557 | E89: =SUM(E84:E88) -> 0.631 | F89: =SUM(F84:F88) -> 0.742 | G89: =SUM(G84:G88) -> 0.789 | H89: =SUM(H84:H88) -> 0.906 | I89: =SUM(I84:I88) -> 1.251
B91: Hire charges
B92: Packing expenses
B93: Communication expenses | C93: 0.025 | D93: 0.172 | E93: 0.116027 | F93: 0.033 | H93: 0.017 | I93: 0.3
B94: Training expenses
B95: Wealth tax
B96: Director's remuneration | C96: 6 | D96: 6.75 | E96: 7.2 | F96: 7.938 | G96: 8.545 | H96: 10.112 | I96: 8.012
B97: Other administration | C97: 0.788 | D97: 1.453 | E97: 6.45778 | F97: 1.085 | G97: 0.948 | H97: 0.983 | I97: 5.679
B98: Stamping and registration
B99: Service charges
B100: Freight outwards
B101: Printing and stationery<>
B102: Depreciation (including lease equalisation) on leased assets
B103: Insurance | C103: 0.532 | D103: 0.324 | E103: 2.604577 | F103: 4.008 | G103: 3.359 | H103: 5.419 | I103: 9.779
B104: Traveling and conveyance | C104: 1.166 | D104: 2.162 | E104: 1.866126 | F104: 1.495 | G104: 3.849 | H104: 13.683 | I104: 16.404
B105: Printing and stationery
B106: General and administration expenses | C106: =SUM(C79,C81:C83,C91:C105,C89) -> 13.575 | D106: =SUM(D79,D81:D83,D91:D105,D89) -> 20.039 | E106: =SUM(E79,E81:E83,E91:E105,E89) -> 29.235321 | F106: =SUM(F79,F81:F83,F91:F105,F89) -> 28.193 | G106: =SUM(G79,G81:G83,G91:G105,G89) -> 28.902 | H106: =SUM(H79,H81:H83,H91:H105,H89) -> 54.341 | I106: =SUM(I79,I81:I83,I91:I105,I89) -> 98.537
B108: Distribution expenses
B109: Advertisement & sales promotion | C109: 0.543 | D109: 0.223 | E109: 0.276502 | F109: 0.164 | G109: 0.287 | H109: 1.357 | I109: 4.047
B110: Sales commissions & incentives | C110: 0.04 | H110: 0.083
B111: Brokerages
B112: Discounts & rebates | C112: 0.05
B113: Freight and forwarding | E113: 0.623642
B114: Handling and clearing charges | C114: 0.094 | D114: 0.242
B115: Selling and distribution expenses | C115: =SUM(C108:C114) -> 0.727 | D115: =SUM(D108:D114) -> 0.465 | E115: =SUM(E108:E114) -> 0.900144 | F115: =SUM(F108:F114) -> 0.164 | G115: =SUM(G108:G114) -> 0.287 | H115: =SUM(H108:H114) -> 1.44 | I115: =SUM(I108:I114) -> 4.047
...

Sheet Detailed CFS
B1: =+Cover!B3 -> Knowledge Marine & Engineering Works Ltd.
B3: Cash Flow - Detailed
B4: Rs mm | C4: Mar-18(A) | D4: Mar-19(A) | E4: Mar-20(A) | F4: Mar-21(A) | G4: Mar-22(A) | H4: Mar-23(A) | I4: Mar-24(A)
C5: Consolidated | D5: Consolidated | E5: Consolidated | F5: Consolidated | G5: Consolidated | H5: Consolidated | I5: Consolidated
B6: Profit before tax | C6: 21.773 | D6: 30.048 | E6: 53.246233 | F6: 94.777 | G6: 280.078 | H6: 633.784 | I6: 429.874
B7: Depreciation | C7: 2.062 | D7: 7.994 | E7: 15.135037 | F7: 20.645 | G7: 24.345 | H7: 43.582 | I7: 60.754
B8: Impairment
B9: Interest expeses | C9: 1.917 | D9: 5.099 | E9: 11.109093 | F9: 17.019 | G9: 24.837 | H9: 23.301 | I9: 39.383
B10: Profit/loss on sale of fixed assets
B11: Profit/loss on sale of investments
B12: Dividend received
B13: Interest income | C13: -0.41 | D13: -0.28 | E13: -0.895735 | F13: -1.2 | G13: -3.645 | H13: -13.804 | I13: -31.221
B14: Diminution in the value / write off of investments
B15: Transferred from revaluation reserve
B16: Effect of exchange rate change | H16: 0.501 | I16: 2.246
B17: Net prior year adjustments
B18: Provision & written off | D18: 3.143 | F18: 0.493 | G18: 0.454 | H18: -0.017
B19: Excess of cost over fair value of investments
B20: Tax paid
B21: Tax refunded
B22: Bad debts irrecoverable written off
B23: Provision for doubtful debts & advances
B24: Misc. expenses written off
B25: Other adjustments | H25: -0.001 | I25: -0.01
B26: Adjustment | C26: =SUM(C7:C25) -> 3.569 | D26: =SUM(D7:D25) -> 15.956 | E26: =SUM(E7:E25) -> 25.348395 | F26: =SUM(F7:F25) -> 36.957 | G26: =SUM(G7:G25) -> 45.991 | H26: =SUM(H7:H25) -> 53.562 | I26: =SUM(I7:I25) -> 71.152
B28: Trade & other receivables | C28: -10.29 | D28: 6.203 | E28: 27.398893 | F28: 26.327 | G28: -35.459 | H28: -519.059 | I28: 123.727
B29: Inventories | F29: -0.603 | G29: 1.41 | H29: -9.538 | I29: -0.74
B30: Loans & advances | C30: -3.304 | D30: 2.221 | E30: -38.700599 | F30: -59.865 | G30: 1.959 | H30: -91.958 | I30: 14.659
B31: Investments | G31: 0.587
B32: Trade & other payables | C32: 22.577 | D32: 71.561 | E32: -42.690545 | F32: -30.766 | G32: 113.614 | H32: 293.407 | I32: -206.841
B33: Decrease / (increase) in lt loans & advances
B34: (increase) / decrease in other non current assets | C34: -0.419 | D34: -10.81
B35: Increase / (decrease) in other non current liabilities
B36: Increase / (decrease) in lt provisions | H36: 0.69 | I36: 0.495
B37: Others
B38: Changes in working capital | C38: =SUM(C28:C37) -> 8.564 | D38: =SUM(D28:D37) -> 69.175 | E38: =SUM(E28:E37) -> -53.992251 | F38: =SUM(F28:F37) -> -64.907 | G38: =SUM(G28:G37) -> 82.111 | H38: =SUM(H28:H37) -> -326.458 | I38: =SUM(I28:I37) -> -68.7
B41: Cash flow after changes in working capital | C41: =C6+C26+C38 -> 33.906 | D41: =D6+D26+D38 -> 115.179 | E41: =E6+E26+E38 -> 24.602377 | F41: =F6+F26+F38 -> 66.827 | G41: =G6+G26+G38 -> 408.18 | H41: =H6+H26+H38 -> 360.888 | I41: =I6+I26+I38 -> 432.326
B42: Interest paid
B43: Tax paid | C43: -3.707 | D43: -2.998 | E43: -4.916059 | F43: -18.539 | G43: -62.262 | H43: -148.708 | I43: -88.119
B44: Other direct expenses paid
B45: Extra & other item
B46: Cash from operating activities | C46: =SUM(C41:C45) -> 30.199 | D46: =SUM(D41:D45) -> 112.181 | E46: =SUM(E41:E45) -> 19.686318 | F46: =SUM(F41:F45) -> 48.288 | G46: =SUM(G41:G45) -> 345.918 | H46: =SUM(H41:H45) -> 212.18 | I46: =SUM(I41:I45) -> 344.207
B48: Purchase of fixed assets | C48: -109.967 | D48: -96.066 | E48: -165.89582 | F48: -25.535 | G48: -290.822 | H48: -178.433 | I48: -621.928
B49: Sale of fixed assets | D49: 1.25 | F49: 11.393
B50: Profit/loss on sale of fixed assets
B51: Profit/loss on sale of investments
B52: Purchase of investment | E52: -2.52665
B53: Sale of investments | C53: 5.795 | E53: 0.895735
B54: Investment in subsidiaries
B55: Dividend income
B56: Interest received | C56: 0.41 | D56: 0.28 | F56: 1.18 | G56: 3.645 | H56: 13.804 | I56: 31.221
B57: Increase/ decrease in loans
B58: Loans & advances given to subsidiaries / partnership firms etc.
B59: Advances for capital expenditure | E59: 75.286291 | F59: -28.536 | G59: -18.08 | H59: -62.905 | I59: -128.852
B60: Inter corporate deposits
B61: Other investment activities
B62: Cash flow from investing activities | C62: =SUM(C48:C61) -> -103.762 | D62: =SUM(D48:D61) -> -94.536 | E62: =SUM(E48:E61) -> -92.240448 | F62: =SUM(F48:F61) -> -41.498 | G62: =SUM(G48:G61) -> -305.257 | H62: =SUM(H48:H61) -> -227.534 | I62: =SUM(I48:I61) -> -719.559
B64: Increase / (decrease) in loan funds | C64: 67.378 | E64: 73.373662
B65: Proceeds from long term borrowings | D65: 30.94 | G65: 55.405 | I65: 375.421
B66: Repayment of long term borrowings | H66: -129.699
B67: Proceeds from debenture / bonds
B68: Repayment of debenture / bonds
B69: Short term loans | D69: 4.066 | F69: 8.097 | G69: 39.148 | H69: 107.068 | I69: -14.829
B70: Increase / (decrease) in preference capital
B71: Proceeds from preference shares capital
B72: Redemption of preference shares capital
B73: Proceeds from shares warrants
B74: Proceeds from issue of equity share capital | D74: 24.9 | F74: 101.232 | H74: 395.5 | I74: 0.23
B75: Buy back of equity shares capital
B76: Equity dividend paid
B77: Preference dividend
B78: Interest paid | C78: -1.917 | D78: -5.099 | E78: -11.109093 | F78: -17.019 | G78: -24.837 | H78: -23.301 | I78: -39.383
B79: Changes in working capital borrowings
B80: Loans (to) / from subsidiaries
B81: Net inc/dec in cash / export credit facilities and other short term loans
B82: Income tax on dividend paid
B83: Expenses on issue of shares
B84: Other financial activities | C84: 7.53 | E84: -45.025663
B85: Cash from financing activities | C85: =SUM(C64:C84) -> 72.991 | D85: =SUM(D64:D84) -> 54.807 | E85: =SUM(E64:E84) -> 17.238906 | F85: =SUM(F64:F84) -> 92.31 | G85: =SUM(G64:G84) -> 69.716 | H85: =SUM(H64:H84) -> 349.568 | I85: =SUM(I64:I84) -> 321.439
B87: Net cash inflow / outflow | C87: =SUM(C46,C62,C85) -> -0.572 | D87: =SUM(D46,D62,D85) -> 72.452 | E87: =SUM(E46,E62,E85) -> -55.315224 | F87: =SUM(F46,F62,F85) -> 99.1 | G87: =SUM(G46,G62,G85) -> 110.377 | H87: =SUM(H46,H62,H85) -> 334.214 | I87: =SUM(I46,I62,I85) -> -53.913
B88: Opening cash & cash equivalents | C88: 2.324 | D88: 1.751 | E88: 71.528385 | F88: 16.212 | G88: 115.312 | H88: 225.691 | I88: 559.905
B89: Cash & cash equivalent on amalgamation / take over / merger
B90: Cash & cash equivalent of subsidiaries under liquidations
B91: Translation adj. on reserves / op cash balances frgn subsidiaries
B92: Effect of foreign exchange fluctuations
B93: Closing cash & cash equivalent | C93: =SUM(C86:C91) -> 1.752 | D93: =SUM(D86:D91) -> 74.203 | E93: =SUM(E86:E91) -> 16.213161 | F93: =SUM(F86:F91) -> 115.312 | G93: =SUM(G86:G91) -> 225.689 | H93: =SUM(H86:H91) -> 559.905 | I93: =SUM(I86:I91) -> 505.992
